{
  "date": "2026-04-28",
  "sport": "handball",
  "generatedAt": "2026-04-28T04:02:52.378155",
  "stats": {
    "total": 13,
    "qualifying": 2,
    "formAdvantage": 1
  },
  "matches": [
    {
      "id": -451734076637982843,
      "homeTeam": "Mistra",
      "awayTeam": "Viljandi",
      "time": "28.04.2026 16:00",
      "date": "2026-04-28",
      "league": null,
      "country": "",
      "sport": "handball",
      "matchUrl": "https://www.livesport.com/pl/mecz/pilka-reczna/mistra-OdPe0NWQ/viljandi-nujEStKN/?mid=44SKKzdE",
      "qualifies": false,
      "h2h": {
        "home": 2,
        "draw": 0,
        "away": 3,
        "total": 5,
        "winRate": 40
      },
      "homeForm": [],
      "awayForm": [],
      "homeFormHome": [],
      "awayFormAway": [],
      "formAdvantage": false,
      "odds": null,
      "forebet": null,
      "sofascore": null,
      "focusTeam": "home",
      "scoring": null,
      "tennis": null,
      "confidence": 0,
      "value_bet": false
    },
    {
      "id": 5227388602850578832,
      "homeTeam": "Nexe",
      "awayTeam": "Kiel",
      "time": "28.04.2026 16:45",
      "date": "2026-04-28",
      "league": null,
      "country": "",
      "sport": "handball",
      "matchUrl": "https://www.livesport.com/pl/mecz/pilka-reczna/kiel-ptjyzCDl/nexe-0lleY8B7/?mid=C6wuGFh5",
      "qualifies": false,
      "h2h": {
        "home": 0,
        "draw": 0,
        "away": 2,
        "total": 2,
        "winRate": 0
      },
      "homeForm": [],
      "awayForm": [],
      "homeFormHome": [],
      "awayFormAway": [],
      "formAdvantage": false,
      "odds": null,
      "forebet": null,
      "sofascore": null,
      "focusTeam": "home",
      "scoring": null,
      "tennis": null,
      "confidence": 0,
      "value_bet": false
    },
    {
      "id": -4220326074154319543,
      "homeTeam": "Montpellier",
      "awayTeam": "Vardar 1961",
      "time": "28.04.2026 18:45",
      "date": "2026-04-28",
      "league": null,
      "country": "",
      "sport": "handball",
      "matchUrl": "https://www.livesport.com/pl/mecz/pilka-reczna/montpellier-Qopo6dYu/vardar-skopje-2gCg4P0D/?mid=r3ccO6gn",
      "qualifies": false,
      "h2h": {
        "home": 2,
        "draw": 0,
        "away": 3,
        "total": 5,
        "winRate": 40
      },
      "homeForm": [],
      "awayForm": [],
      "homeFormHome": [],
      "awayFormAway": [],
      "formAdvantage": false,
      "odds": null,
      "forebet": null,
      "sofascore": null,
      "focusTeam": "home",
      "scoring": null,
      "tennis": null,
      "confidence": 0,
      "value_bet": false
    },
    {
      "id": 6599124672564531271,
      "homeTeam": "MT Melsungen",
      "awayTeam": "Porto",
      "time": "28.04.2026 18:45",
      "date": "2026-04-28",
      "league": null,
      "country": "",
      "sport": "handball",
      "matchUrl": "https://www.livesport.com/pl/mecz/pilka-reczna/melsungen-zVrlX9c7/porto-Y9S5LRQA/?mid=8xqhApMq",
      "qualifies": true,
      "h2h": {
        "home": 3,
        "draw": 0,
        "away": 0,
        "total": 3,
        "winRate": 100
      },
      "homeForm": [
        "L",
        "W",
        "W",
        "W",
        "L"
      ],
      "awayForm": [
        "W",
        "W",
        "L",
        "W",
        "W"
      ],
      "homeFormHome": [
        "W",
        "W",
        "W",
        "L",
        "L"
      ],
      "awayFormAway": [
        "W",
        "L",
        "W",
        "W",
        "W"
      ],
      "formAdvantage": false,
      "odds": {
        "home": 1.4,
        "draw": 9.0,
        "away": 3.4,
        "bookmaker": "Pinnacle"
      },
      "forebet": {
        "prediction": "1",
        "probability": 57.0,
        "exactScore": "34-32",
        "overUnder": null,
        "btts": null,
        "homeProb": null,
        "drawProb": null,
        "awayProb": null
      },
      "sofascore": null,
      "focusTeam": "home",
      "scoring": {
        "pick": "X",
        "prob": 11.8,
        "ev": 0.064,
        "edge": 0.7,
        "kelly": 0.8,
        "confidence": 37.0,
        "dataQuality": 0.7
      },
      "tennis": null,
      "confidence": 37.0,
      "value_bet": true
    },
    {
      "id": -8166987456215414493,
      "homeTeam": "Beti-Onak K",
      "awayTeam": "Malaga K",
      "time": "28.04.2026 17:00",
      "date": "2026-04-28",
      "league": null,
      "country": "",
      "sport": "handball",
      "matchUrl": "https://www.livesport.com/pl/mecz/pilka-reczna/beti-onak-vZGbi5U2/malaga-IZYftq3q/?mid=WzA98HwC",
      "qualifies": false,
      "h2h": {
        "home": 0,
        "draw": 0,
        "away": 4,
        "total": 5,
        "winRate": 0
      },
      "homeForm": [],
      "awayForm": [],
      "homeFormHome": [],
      "awayFormAway": [],
      "formAdvantage": false,
      "odds": null,
      "forebet": null,
      "sofascore": null,
      "focusTeam": "home",
      "scoring": null,
      "tennis": null,
      "confidence": 0,
      "value_bet": false
    },
    {
      "id": 282176192010590527,
      "homeTeam": "IBV K",
      "awayTeam": "Haukar K",
      "time": "28.04.2026 18:00",
      "date": "2026-04-28",
      "league": null,
      "country": "",
      "sport": "handball",
      "matchUrl": "https://www.livesport.com/pl/mecz/pilka-reczna/haukar-jF3jiyp8/ibv-vestmannaeyjar-t29N3xJn/?mid=IFvQWBn9",
      "qualifies": false,
      "h2h": {
        "home": 2,
        "draw": 0,
        "away": 3,
        "total": 5,
        "winRate": 40
      },
      "homeForm": [],
      "awayForm": [],
      "homeFormHome": [],
      "awayFormAway": [],
      "formAdvantage": false,
      "odds": null,
      "forebet": null,
      "sofascore": null,
      "focusTeam": "home",
      "scoring": null,
      "tennis": null,
      "confidence": 0,
      "value_bet": false
    },
    {
      "id": -7797071992235767315,
      "homeTeam": "Ohrid",
      "awayTeam": "Butel Skopje",
      "time": "28.04.2026 16:00",
      "date": "2026-04-28",
      "league": null,
      "country": "",
      "sport": "handball",
      "matchUrl": "https://www.livesport.com/pl/mecz/pilka-reczna/butel-skopje-8Oa01Lv7/ohrid-WrdN2B8B/?mid=8KiWTq8B",
      "qualifies": true,
      "h2h": {
        "home": 4,
        "draw": 0,
        "away": 1,
        "total": 5,
        "winRate": 80
      },
      "homeForm": [
        "L",
        "W",
        "W",
        "W",
        "L"
      ],
      "awayForm": [
        "L",
        "L",
        "L",
        "L",
        "L"
      ],
      "homeFormHome": [
        "W",
        "W",
        "D",
        "W",
        "W"
      ],
      "awayFormAway": [
        "L",
        "W",
        "W",
        "L",
        "W"
      ],
      "formAdvantage": true,
      "odds": null,
      "forebet": {
        "prediction": "1",
        "probability": 78.0,
        "exactScore": "32-23",
        "overUnder": null,
        "btts": null,
        "homeProb": null,
        "drawProb": null,
        "awayProb": null
      },
      "sofascore": null,
      "focusTeam": "home",
      "scoring": {
        "pick": "1",
        "prob": 70.5,
        "ev": -999.0,
        "edge": 0.0,
        "kelly": 0.0,
        "confidence": 46.0,
        "dataQuality": 0.6
      },
      "tennis": null,
      "confidence": 46.0,
      "value_bet": false
    },
    {
      "id": 825278507239935061,
      "homeTeam": "Lillestrøm",
      "awayTeam": "Reistad",
      "time": "28.04.2026 17:00",
      "date": "2026-04-28",
      "league": null,
      "country": "",
      "sport": "handball",
      "matchUrl": "https://www.livesport.com/pl/mecz/pilka-reczna/lillestr-m-6yKG2JE1/reistad-jL3xdLXH/?mid=Wd9px365",
      "qualifies": false,
      "h2h": {
        "home": 0,
        "draw": 0,
        "away": 0,
        "total": 0,
        "winRate": 0
      },
      "homeForm": [],
      "awayForm": [],
      "homeFormHome": [],
      "awayFormAway": [],
      "formAdvantage": false,
      "odds": null,
      "forebet": null,
      "sofascore": null,
      "focusTeam": "home",
      "scoring": null,
      "tennis": null,
      "confidence": 0,
      "value_bet": false
    },
    {
      "id": -2145351411384490885,
      "homeTeam": "Orlęta Zwoleń",
      "awayTeam": "Lider Radom",
      "time": "28.04.2026 17:30",
      "date": "2026-04-28",
      "league": null,
      "country": "",
      "sport": "handball",
      "matchUrl": "https://www.livesport.com/pl/mecz/pilka-reczna/lider-radom-p408q3ff/orleta-zwolen-KA0ays3T/?mid=O82HeTx9",
      "qualifies": false,
      "h2h": {
        "home": 0,
        "draw": 0,
        "away": 1,
        "total": 1,
        "winRate": 0
      },
      "homeForm": [],
      "awayForm": [],
      "homeFormHome": [],
      "awayFormAway": [],
      "formAdvantage": false,
      "odds": null,
      "forebet": null,
      "sofascore": null,
      "focusTeam": "home",
      "scoring": null,
      "tennis": null,
      "confidence": 0,
      "value_bet": false
    },
    {
      "id": -6857593569400147712,
      "homeTeam": "Handball Warszawa K",
      "awayTeam": "Dziewiątka Legnica K",
      "time": "28.04.2026 17:00",
      "date": "2026-04-28",
      "league": null,
      "country": "",
      "sport": "handball",
      "matchUrl": "https://www.livesport.com/pl/mecz/pilka-reczna/dziewiatka-legnica-Y5GWYR2B/handball-warszawa-On1ycmxG/?mid=4CRzRY3d",
      "qualifies": false,
      "h2h": {
        "home": 2,
        "draw": 0,
        "away": 3,
        "total": 5,
        "winRate": 40
      },
      "homeForm": [],
      "awayForm": [],
      "homeFormHome": [],
      "awayFormAway": [],
      "formAdvantage": false,
      "odds": null,
      "forebet": null,
      "sofascore": null,
      "focusTeam": "home",
      "scoring": null,
      "tennis": null,
      "confidence": 0,
      "value_bet": false
    },
    {
      "id": -6539432794283553633,
      "homeTeam": "SMS ZPRP Płock K",
      "awayTeam": "Kielce K",
      "time": "28.04.2026 18:00",
      "date": "2026-04-28",
      "league": null,
      "country": "",
      "sport": "handball",
      "matchUrl": "https://www.livesport.com/pl/mecz/pilka-reczna/korona-kielce-QZJIf9iC/sms-zprp-plock-W0az8Xxo/?mid=Eyha5WLH",
      "qualifies": false,
      "h2h": {
        "home": 1,
        "draw": 0,
        "away": 4,
        "total": 5,
        "winRate": 20
      },
      "homeForm": [],
      "awayForm": [],
      "homeFormHome": [],
      "awayFormAway": [],
      "formAdvantage": false,
      "odds": null,
      "forebet": null,
      "sofascore": null,
      "focusTeam": "home",
      "scoring": null,
      "tennis": null,
      "confidence": 0,
      "value_bet": false
    },
    {
      "id": -4116014272899876196,
      "homeTeam": "Mihaliccik",
      "awayTeam": "Rize Genclik",
      "time": "28.04.2026 13:00",
      "date": "2026-04-28",
      "league": null,
      "country": "",
      "sport": "handball",
      "matchUrl": "https://www.livesport.com/pl/mecz/pilka-reczna/mihaliccik-bld-sk-0I5ux0dt/rize-genclik-MiezYFHj/?mid=IVMHJUhJ",
      "qualifies": false,
      "h2h": {
        "home": 2,
        "draw": 0,
        "away": 1,
        "total": 5,
        "winRate": 40
      },
      "homeForm": [],
      "awayForm": [],
      "homeFormHome": [],
      "awayFormAway": [],
      "formAdvantage": false,
      "odds": null,
      "forebet": null,
      "sofascore": null,
      "focusTeam": "home",
      "scoring": null,
      "tennis": null,
      "confidence": 0,
      "value_bet": false
    },
    {
      "id": -3084708948417686970,
      "homeTeam": "Esztergomi K",
      "awayTeam": "Ferencvaros K",
      "time": "28.04.2026 16:00",
      "date": "2026-04-28",
      "league": null,
      "country": "",
      "sport": "handball",
      "matchUrl": "https://www.livesport.com/pl/mecz/pilka-reczna/esztergomi-phzrmPsE/ferencvaros-0dh6rrzn/?mid=Qiq8ZSFi",
      "qualifies": false,
      "h2h": {
        "home": 0,
        "draw": 0,
        "away": 4,
        "total": 4,
        "winRate": 0
      },
      "homeForm": [],
      "awayForm": [],
      "homeFormHome": [],
      "awayFormAway": [],
      "formAdvantage": false,
      "odds": null,
      "forebet": null,
      "sofascore": null,
      "focusTeam": "home",
      "scoring": null,
      "tennis": null,
      "confidence": 0,
      "value_bet": false
    }
  ]
}