{
  "date": "2026-06-17",
  "sport": "volleyball",
  "generatedAt": "2026-06-17T05:07:18.148710",
  "stats": {
    "total": 9,
    "qualifying": 0,
    "formAdvantage": 0
  },
  "matches": [
    {
      "id": 3604055440026779345,
      "homeTeam": "Dominikana K",
      "awayTeam": "USA K",
      "time": "17.06.2026 04:00",
      "date": "2026-06-17",
      "league": null,
      "country": "",
      "sport": "volleyball",
      "matchUrl": "https://www.livesport.com/pl/mecz/siatkowka/dominikana-d2lhyw6E/usa-nmZgEFb1/?mid=4I9bnpUI",
      "qualifies": false,
      "h2h": {
        "home": 0,
        "draw": 0,
        "away": 0,
        "total": 0,
        "winRate": 0
      },
      "homeForm": [],
      "awayForm": [],
      "homeFormHome": [],
      "awayFormAway": [],
      "formAdvantage": false,
      "odds": null,
      "forebet": null,
      "sofascore": null,
      "focusTeam": "home",
      "scoring": null,
      "tennis": null,
      "confidence": 0,
      "value_bet": false
    },
    {
      "id": -5349803528898702524,
      "homeTeam": "Kanada K",
      "awayTeam": "Holandia K",
      "time": "17.06.2026 06:00",
      "date": "2026-06-17",
      "league": null,
      "country": "",
      "sport": "volleyball",
      "matchUrl": "https://www.livesport.com/pl/mecz/siatkowka/holandia-IJV0507F/kanada-lfUBJBCe/?mid=UcQ9g1yn",
      "qualifies": false,
      "h2h": {
        "home": 0,
        "draw": 0,
        "away": 0,
        "total": 0,
        "winRate": 0
      },
      "homeForm": [],
      "awayForm": [],
      "homeFormHome": [],
      "awayFormAway": [],
      "formAdvantage": false,
      "odds": null,
      "forebet": null,
      "sofascore": null,
      "focusTeam": "home",
      "scoring": null,
      "tennis": null,
      "confidence": 0,
      "value_bet": false
    },
    {
      "id": -5588348855000816045,
      "homeTeam": "Czechy K",
      "awayTeam": "Włochy K",
      "time": "17.06.2026 08:00",
      "date": "2026-06-17",
      "league": null,
      "country": "",
      "sport": "volleyball",
      "matchUrl": "https://www.livesport.com/pl/mecz/siatkowka/czechy-8dhw5vxS/wlochy-WOxNzHzR/?mid=M5rHiu6b",
      "qualifies": false,
      "h2h": {
        "home": 0,
        "draw": 0,
        "away": 0,
        "total": 0,
        "winRate": 0
      },
      "homeForm": [],
      "awayForm": [],
      "homeFormHome": [],
      "awayFormAway": [],
      "formAdvantage": false,
      "odds": null,
      "forebet": null,
      "sofascore": null,
      "focusTeam": "home",
      "scoring": null,
      "tennis": null,
      "confidence": 0,
      "value_bet": false
    },
    {
      "id": -2646417306491537506,
      "homeTeam": "Niemcy K",
      "awayTeam": "Chiny K",
      "time": "17.06.2026 09:30",
      "date": "2026-06-17",
      "league": null,
      "country": "",
      "sport": "volleyball",
      "matchUrl": "https://www.livesport.com/pl/mecz/siatkowka/chiny-vDjLFHEr/niemcy-d4sh7Mx3/?mid=fJtPkJzB",
      "qualifies": false,
      "h2h": {
        "home": 0,
        "draw": 0,
        "away": 0,
        "total": 0,
        "winRate": 0
      },
      "homeForm": [],
      "awayForm": [],
      "homeFormHome": [],
      "awayFormAway": [],
      "formAdvantage": false,
      "odds": null,
      "forebet": null,
      "sofascore": null,
      "focusTeam": "home",
      "scoring": null,
      "tennis": null,
      "confidence": 0,
      "value_bet": false
    },
    {
      "id": -2656587896807659660,
      "homeTeam": "Bułgaria K",
      "awayTeam": "Polska K",
      "time": "17.06.2026 10:00",
      "date": "2026-06-17",
      "league": null,
      "country": "",
      "sport": "volleyball",
      "matchUrl": "https://www.livesport.com/pl/mecz/siatkowka/bulgaria-p8EJiqgc/polska-EwV50bpq/?mid=2qpXmc5N",
      "qualifies": false,
      "h2h": {
        "home": 0,
        "draw": 0,
        "away": 0,
        "total": 0,
        "winRate": 0
      },
      "homeForm": [],
      "awayForm": [],
      "homeFormHome": [],
      "awayFormAway": [],
      "formAdvantage": false,
      "odds": null,
      "forebet": null,
      "sofascore": null,
      "focusTeam": "home",
      "scoring": null,
      "tennis": null,
      "confidence": 0,
      "value_bet": false
    },
    {
      "id": 407490030457849138,
      "homeTeam": "Japonia K",
      "awayTeam": "Serbia K",
      "time": "17.06.2026 12:00",
      "date": "2026-06-17",
      "league": null,
      "country": "",
      "sport": "volleyball",
      "matchUrl": "https://www.livesport.com/pl/mecz/siatkowka/japonia-YotoKc6R/serbia-WCU4k1hM/?mid=YRz3ryTp",
      "qualifies": false,
      "h2h": {
        "home": 0,
        "draw": 0,
        "away": 0,
        "total": 0,
        "winRate": 0
      },
      "homeForm": [],
      "awayForm": [],
      "homeFormHome": [],
      "awayFormAway": [],
      "formAdvantage": false,
      "odds": null,
      "forebet": null,
      "sofascore": null,
      "focusTeam": "home",
      "scoring": null,
      "tennis": null,
      "confidence": 0,
      "value_bet": false
    },
    {
      "id": -8979256354636505518,
      "homeTeam": "Francja K",
      "awayTeam": "Brazylia K",
      "time": "17.06.2026 13:00",
      "date": "2026-06-17",
      "league": null,
      "country": "",
      "sport": "volleyball",
      "matchUrl": "https://www.livesport.com/pl/mecz/siatkowka/brazylia-hYwJycLK/francja-WSCmiNN9/?mid=QLNl6vLi",
      "qualifies": false,
      "h2h": {
        "home": 0,
        "draw": 0,
        "away": 0,
        "total": 0,
        "winRate": 0
      },
      "homeForm": [],
      "awayForm": [],
      "homeFormHome": [],
      "awayFormAway": [],
      "formAdvantage": false,
      "odds": null,
      "forebet": null,
      "sofascore": null,
      "focusTeam": "home",
      "scoring": null,
      "tennis": null,
      "confidence": 0,
      "value_bet": false
    },
    {
      "id": 2577365516712193784,
      "homeTeam": "Tajlandia K",
      "awayTeam": "Ukraina K",
      "time": "17.06.2026 13:30",
      "date": "2026-06-17",
      "league": null,
      "country": "",
      "sport": "volleyball",
      "matchUrl": "https://www.livesport.com/pl/mecz/siatkowka/tajlandia-dpagYtgn/ukraina-jTaSdicD/?mid=CxMd4Ik4",
      "qualifies": false,
      "h2h": {
        "home": 0,
        "draw": 0,
        "away": 0,
        "total": 0,
        "winRate": 0
      },
      "homeForm": [],
      "awayForm": [],
      "homeFormHome": [],
      "awayFormAway": [],
      "formAdvantage": false,
      "odds": null,
      "forebet": null,
      "sofascore": null,
      "focusTeam": "home",
      "scoring": null,
      "tennis": null,
      "confidence": 0,
      "value_bet": false
    },
    {
      "id": 7654181552347758111,
      "homeTeam": "Turcja K",
      "awayTeam": "Belgia K",
      "time": "17.06.2026 16:30",
      "date": "2026-06-17",
      "league": null,
      "country": "",
      "sport": "volleyball",
      "matchUrl": "https://www.livesport.com/pl/mecz/siatkowka/belgia-hbcYyRiJ/turcja-QZT8lL7S/?mid=K2P42dKG",
      "qualifies": false,
      "h2h": {
        "home": 0,
        "draw": 0,
        "away": 0,
        "total": 0,
        "winRate": 0
      },
      "homeForm": [],
      "awayForm": [],
      "homeFormHome": [],
      "awayFormAway": [],
      "formAdvantage": false,
      "odds": null,
      "forebet": null,
      "sofascore": null,
      "focusTeam": "home",
      "scoring": null,
      "tennis": null,
      "confidence": 0,
      "value_bet": false
    }
  ]
}