{
  "date": "2026-02-14",
  "sport": "tennis",
  "generatedAt": "2026-02-14T02:30:31.212422",
  "stats": {
    "total": 122,
    "qualifying": 57,
    "formAdvantage": 0
  },
  "matches": [
    {
      "id": 602384730829478768,
      "homeTeam": "Martinez P.",
      "awayTeam": "Darderi L.",
      "time": "",
      "date": "2026-02-14",
      "league": "",
      "country": "",
      "sport": "tennis",
      "matchUrl": "",
      "qualifies": true,
      "h2h": {
        "home": 1,
        "draw": 0,
        "away": 0,
        "total": 4,
        "winRate": 75
      },
      "homeForm": [
        "L",
        "L",
        "W",
        "L",
        "L"
      ],
      "awayForm": [
        "W",
        "W",
        "L",
        "W",
        "W"
      ],
      "homeFormHome": [],
      "awayFormAway": [],
      "formAdvantage": false,
      "odds": null,
      "forebet": {
        "prediction": "2",
        "probability": 65.0,
        "exactScore": null,
        "overUnder": null,
        "btts": null
      },
      "sofascore": {
        "home": 11,
        "draw": null,
        "away": 89,
        "votes": 4934
      },
      "focusTeam": "home"
    },
    {
      "id": -3923443854714422782,
      "homeTeam": "Cerundolo F.",
      "awayTeam": "Etcheverry T. M.",
      "time": "",
      "date": "2026-02-14",
      "league": "",
      "country": "",
      "sport": "tennis",
      "matchUrl": "",
      "qualifies": false,
      "h2h": {
        "home": 3,
        "draw": 0,
        "away": 0,
        "total": 5,
        "winRate": 60
      },
      "homeForm": [
        "W",
        "W",
        "L",
        "L",
        "W"
      ],
      "awayForm": [
        "L",
        "L",
        "W",
        "W",
        "L"
      ],
      "homeFormHome": [],
      "awayFormAway": [],
      "formAdvantage": false,
      "odds": null,
      "forebet": null,
      "sofascore": null,
      "focusTeam": "home"
    },
    {
      "id": 6637925558486453352,
      "homeTeam": "Baez S.",
      "awayTeam": "Darderi L.",
      "time": "",
      "date": "2026-02-14",
      "league": "",
      "country": "",
      "sport": "tennis",
      "matchUrl": "",
      "qualifies": false,
      "h2h": {
        "home": 3,
        "draw": 0,
        "away": 0,
        "total": 5,
        "winRate": 60
      },
      "homeForm": [
        "L",
        "L",
        "W",
        "W",
        "W"
      ],
      "awayForm": [
        "W",
        "W",
        "L",
        "L",
        "L"
      ],
      "homeFormHome": [],
      "awayFormAway": [],
      "formAdvantage": false,
      "odds": null,
      "forebet": null,
      "sofascore": null,
      "focusTeam": "home"
    },
    {
      "id": 4155695013875653634,
      "homeTeam": "Kecmanovic M.",
      "awayTeam": "Shelton B.",
      "time": "",
      "date": "2026-02-14",
      "league": "",
      "country": "",
      "sport": "tennis",
      "matchUrl": "",
      "qualifies": true,
      "h2h": {
        "home": 0,
        "draw": 0,
        "away": 0,
        "total": 0,
        "winRate": 0
      },
      "homeForm": [],
      "awayForm": [],
      "homeFormHome": [],
      "awayFormAway": [],
      "formAdvantage": false,
      "odds": null,
      "forebet": {
        "prediction": "2",
        "probability": 61.0,
        "exactScore": null,
        "overUnder": null,
        "btts": null
      },
      "sofascore": {
        "home": 11,
        "draw": null,
        "away": 89,
        "votes": 6173
      },
      "focusTeam": "home"
    },
    {
      "id": 460440917028991793,
      "homeTeam": "Shapovalov D.",
      "awayTeam": "Davidovich Fokina A.",
      "time": "",
      "date": "2026-02-14",
      "league": "",
      "country": "",
      "sport": "tennis",
      "matchUrl": "",
      "qualifies": false,
      "h2h": {
        "home": 1,
        "draw": 0,
        "away": 0,
        "total": 2,
        "winRate": 50
      },
      "homeForm": [
        "L",
        "W",
        "L",
        "L",
        "L"
      ],
      "awayForm": [
        "W",
        "L",
        "L",
        "L",
        "L"
      ],
      "homeFormHome": [],
      "awayFormAway": [],
      "formAdvantage": false,
      "odds": null,
      "forebet": null,
      "sofascore": null,
      "focusTeam": "home"
    },
    {
      "id": 4594249656175261666,
      "homeTeam": "Fritz T.",
      "awayTeam": "Cilic M.",
      "time": "",
      "date": "2026-02-14",
      "league": "",
      "country": "",
      "sport": "tennis",
      "matchUrl": "",
      "qualifies": true,
      "h2h": {
        "home": 2,
        "draw": 0,
        "away": 0,
        "total": 3,
        "winRate": 66
      },
      "homeForm": [
        "W",
        "L",
        "W",
        "W",
        "W"
      ],
      "awayForm": [
        "L",
        "W",
        "L",
        "L",
        "L"
      ],
      "homeFormHome": [],
      "awayFormAway": [],
      "formAdvantage": false,
      "odds": null,
      "forebet": {
        "prediction": "1",
        "probability": 63.0,
        "exactScore": null,
        "overUnder": null,
        "btts": null
      },
      "sofascore": {
        "home": 68,
        "draw": null,
        "away": 32,
        "votes": 1426
      },
      "focusTeam": "home"
    },
    {
      "id": 3358727005904707456,
      "homeTeam": "De Minaur A.",
      "awayTeam": "Humbert U.",
      "time": "",
      "date": "2026-02-14",
      "league": "",
      "country": "",
      "sport": "tennis",
      "matchUrl": "",
      "qualifies": true,
      "h2h": {
        "home": 4,
        "draw": 0,
        "away": 0,
        "total": 5,
        "winRate": 80
      },
      "homeForm": [
        "W",
        "W",
        "W",
        "L",
        "W"
      ],
      "awayForm": [
        "L",
        "L",
        "L",
        "W",
        "L"
      ],
      "homeFormHome": [],
      "awayFormAway": [],
      "formAdvantage": false,
      "odds": null,
      "forebet": {
        "prediction": "1",
        "probability": 75.0,
        "exactScore": null,
        "overUnder": null,
        "btts": null
      },
      "sofascore": {
        "home": 85,
        "draw": null,
        "away": 15,
        "votes": 3340
      },
      "focusTeam": "home"
    },
    {
      "id": 4401112061017455788,
      "homeTeam": "Bublik A.",
      "awayTeam": "Auger-Aliassime F.",
      "time": "",
      "date": "2026-02-14",
      "league": "",
      "country": "",
      "sport": "tennis",
      "matchUrl": "",
      "qualifies": false,
      "h2h": {
        "home": 2,
        "draw": 0,
        "away": 0,
        "total": 5,
        "winRate": 60
      },
      "homeForm": [
        "L",
        "L",
        "W",
        "L",
        "W"
      ],
      "awayForm": [
        "W",
        "W",
        "L",
        "W",
        "L"
      ],
      "homeFormHome": [],
      "awayFormAway": [],
      "formAdvantage": false,
      "odds": null,
      "forebet": null,
      "sofascore": null,
      "focusTeam": "home"
    },
    {
      "id": -9090758585406622406,
      "homeTeam": "Nishioka Y.",
      "awayTeam": "Wong C.",
      "time": "",
      "date": "2026-02-14",
      "league": "",
      "country": "",
      "sport": "tennis",
      "matchUrl": "",
      "qualifies": true,
      "h2h": {
        "home": 0,
        "draw": 0,
        "away": 0,
        "total": 0,
        "winRate": 0
      },
      "homeForm": [],
      "awayForm": [],
      "homeFormHome": [],
      "awayFormAway": [],
      "formAdvantage": false,
      "odds": null,
      "forebet": {
        "prediction": "1",
        "probability": 52.0,
        "exactScore": null,
        "overUnder": null,
        "btts": null
      },
      "sofascore": {
        "home": 14,
        "draw": null,
        "away": 86,
        "votes": 36
      },
      "focusTeam": "home"
    },
    {
      "id": -977255776224772843,
      "homeTeam": "Wu Y.",
      "awayTeam": "Smith C.",
      "time": "",
      "date": "2026-02-14",
      "league": "",
      "country": "",
      "sport": "tennis",
      "matchUrl": "",
      "qualifies": false,
      "h2h": {
        "home": 0,
        "draw": 0,
        "away": 0,
        "total": 0,
        "winRate": 0
      },
      "homeForm": [],
      "awayForm": [],
      "homeFormHome": [],
      "awayFormAway": [],
      "formAdvantage": false,
      "odds": null,
      "forebet": null,
      "sofascore": null,
      "focusTeam": "home"
    },
    {
      "id": -947278814366990726,
      "homeTeam": "Schoolkate T.",
      "awayTeam": "Cassone M.",
      "time": "",
      "date": "2026-02-14",
      "league": "",
      "country": "",
      "sport": "tennis",
      "matchUrl": "",
      "qualifies": true,
      "h2h": {
        "home": 0,
        "draw": 0,
        "away": 0,
        "total": 0,
        "winRate": 0
      },
      "homeForm": [],
      "awayForm": [],
      "homeFormHome": [],
      "awayFormAway": [],
      "formAdvantage": false,
      "odds": null,
      "forebet": {
        "prediction": "1",
        "probability": 63.0,
        "exactScore": null,
        "overUnder": null,
        "btts": null
      },
      "sofascore": {
        "home": 85,
        "draw": null,
        "away": 15,
        "votes": 26
      },
      "focusTeam": "home"
    },
    {
      "id": -2168710333782911610,
      "homeTeam": "Svajda Z.",
      "awayTeam": "Draxl L.",
      "time": "",
      "date": "2026-02-14",
      "league": "",
      "country": "",
      "sport": "tennis",
      "matchUrl": "",
      "qualifies": false,
      "h2h": {
        "home": 0,
        "draw": 0,
        "away": 0,
        "total": 1,
        "winRate": 100
      },
      "homeForm": [
        "L",
        "L",
        "L",
        "L",
        "L"
      ],
      "awayForm": [
        "W",
        "W",
        "W",
        "W",
        "W"
      ],
      "homeFormHome": [],
      "awayFormAway": [],
      "formAdvantage": false,
      "odds": null,
      "forebet": null,
      "sofascore": null,
      "focusTeam": "home"
    },
    {
      "id": 5781777375743306767,
      "homeTeam": "Mmoh M.",
      "awayTeam": "Hijikata R.",
      "time": "",
      "date": "2026-02-14",
      "league": "",
      "country": "",
      "sport": "tennis",
      "matchUrl": "",
      "qualifies": false,
      "h2h": {
        "home": 1,
        "draw": 0,
        "away": 0,
        "total": 1,
        "winRate": 100
      },
      "homeForm": [
        "W",
        "W",
        "W",
        "W",
        "W"
      ],
      "awayForm": [
        "L",
        "L",
        "L",
        "L",
        "L"
      ],
      "homeFormHome": [],
      "awayFormAway": [],
      "formAdvantage": false,
      "odds": null,
      "forebet": null,
      "sofascore": null,
      "focusTeam": "home"
    },
    {
      "id": -8102312777061640403,
      "homeTeam": "Svrcina D.",
      "awayTeam": "Mejia N.",
      "time": "",
      "date": "2026-02-14",
      "league": "",
      "country": "",
      "sport": "tennis",
      "matchUrl": "",
      "qualifies": true,
      "h2h": {
        "home": 1,
        "draw": 0,
        "away": 0,
        "total": 1,
        "winRate": 100
      },
      "homeForm": [
        "W",
        "W",
        "W",
        "W",
        "W"
      ],
      "awayForm": [
        "L",
        "L",
        "L",
        "L",
        "L"
      ],
      "homeFormHome": [],
      "awayFormAway": [],
      "formAdvantage": false,
      "odds": null,
      "forebet": {
        "prediction": "2",
        "probability": 53.0,
        "exactScore": null,
        "overUnder": null,
        "btts": null
      },
      "sofascore": {
        "home": 96,
        "draw": null,
        "away": 4,
        "votes": 24
      },
      "focusTeam": "home"
    },
    {
      "id": 4068303831156975022,
      "homeTeam": "Willwerth B.",
      "awayTeam": "Shimabukuro S.",
      "time": "",
      "date": "2026-02-14",
      "league": "",
      "country": "",
      "sport": "tennis",
      "matchUrl": "",
      "qualifies": true,
      "h2h": {
        "home": 0,
        "draw": 0,
        "away": 0,
        "total": 0,
        "winRate": 0
      },
      "homeForm": [],
      "awayForm": [],
      "homeFormHome": [],
      "awayFormAway": [],
      "formAdvantage": false,
      "odds": null,
      "forebet": {
        "prediction": "2",
        "probability": 53.0,
        "exactScore": null,
        "overUnder": null,
        "btts": null
      },
      "sofascore": {
        "home": 4,
        "draw": null,
        "away": 96,
        "votes": 23
      },
      "focusTeam": "home"
    },
    {
      "id": 3104330047955846069,
      "homeTeam": "Walton A.",
      "awayTeam": "Moreno De Alboran N.",
      "time": "",
      "date": "2026-02-14",
      "league": "",
      "country": "",
      "sport": "tennis",
      "matchUrl": "",
      "qualifies": true,
      "h2h": {
        "home": 1,
        "draw": 0,
        "away": 0,
        "total": 1,
        "winRate": 100
      },
      "homeForm": [
        "W",
        "W",
        "W",
        "W",
        "W"
      ],
      "awayForm": [
        "L",
        "L",
        "L",
        "L",
        "L"
      ],
      "homeFormHome": [],
      "awayFormAway": [],
      "formAdvantage": false,
      "odds": null,
      "forebet": {
        "prediction": "1",
        "probability": 75.0,
        "exactScore": null,
        "overUnder": null,
        "btts": null
      },
      "sofascore": {
        "home": 93,
        "draw": null,
        "away": 7,
        "votes": 27
      },
      "focusTeam": "home"
    },
    {
      "id": 4895553145957904170,
      "homeTeam": "Halys Q.",
      "awayTeam": "Alkaya M.",
      "time": "",
      "date": "2026-02-14",
      "league": "",
      "country": "",
      "sport": "tennis",
      "matchUrl": "",
      "qualifies": true,
      "h2h": {
        "home": 0,
        "draw": 0,
        "away": 0,
        "total": 0,
        "winRate": 0
      },
      "homeForm": [],
      "awayForm": [],
      "homeFormHome": [],
      "awayFormAway": [],
      "formAdvantage": false,
      "odds": null,
      "forebet": {
        "prediction": "1",
        "probability": 63.0,
        "exactScore": null,
        "overUnder": null,
        "btts": null
      },
      "sofascore": {
        "home": 94,
        "draw": null,
        "away": 6,
        "votes": 996
      },
      "focusTeam": "home"
    },
    {
      "id": -5746255094430678405,
      "homeTeam": "McCabe J.",
      "awayTeam": "Choinski J.",
      "time": "",
      "date": "2026-02-14",
      "league": "",
      "country": "",
      "sport": "tennis",
      "matchUrl": "",
      "qualifies": true,
      "h2h": {
        "home": 0,
        "draw": 0,
        "away": 0,
        "total": 0,
        "winRate": 0
      },
      "homeForm": [],
      "awayForm": [],
      "homeFormHome": [],
      "awayFormAway": [],
      "formAdvantage": false,
      "odds": null,
      "forebet": {
        "prediction": "1",
        "probability": 53.0,
        "exactScore": null,
        "overUnder": null,
        "btts": null
      },
      "sofascore": {
        "home": 46,
        "draw": null,
        "away": 54,
        "votes": 782
      },
      "focusTeam": "home"
    },
    {
      "id": -2974557321372198086,
      "homeTeam": "Mochizuki S.",
      "awayTeam": "Al-Sulaiti G.",
      "time": "",
      "date": "2026-02-14",
      "league": "",
      "country": "",
      "sport": "tennis",
      "matchUrl": "",
      "qualifies": false,
      "h2h": {
        "home": 0,
        "draw": 0,
        "away": 0,
        "total": 0,
        "winRate": 0
      },
      "homeForm": [],
      "awayForm": [],
      "homeFormHome": [],
      "awayFormAway": [],
      "formAdvantage": false,
      "odds": null,
      "forebet": null,
      "sofascore": null,
      "focusTeam": "home"
    },
    {
      "id": 3645649313961728802,
      "homeTeam": "Vukic A.",
      "awayTeam": "Herbert P.H.",
      "time": "",
      "date": "2026-02-14",
      "league": "",
      "country": "",
      "sport": "tennis",
      "matchUrl": "",
      "qualifies": false,
      "h2h": {
        "home": 0,
        "draw": 0,
        "away": 0,
        "total": 1,
        "winRate": 100
      },
      "homeForm": [
        "L",
        "L",
        "L",
        "L",
        "L"
      ],
      "awayForm": [
        "W",
        "W",
        "W",
        "W",
        "W"
      ],
      "homeFormHome": [],
      "awayFormAway": [],
      "formAdvantage": false,
      "odds": null,
      "forebet": null,
      "sofascore": null,
      "focusTeam": "home"
    },
    {
      "id": 3375037635293508200,
      "homeTeam": "Basilaszwili N.",
      "awayTeam": "Virtanen O.",
      "time": "",
      "date": "2026-02-14",
      "league": "",
      "country": "",
      "sport": "tennis",
      "matchUrl": "",
      "qualifies": false,
      "h2h": {
        "home": 0,
        "draw": 0,
        "away": 0,
        "total": 0,
        "winRate": 0
      },
      "homeForm": [],
      "awayForm": [],
      "homeFormHome": [],
      "awayFormAway": [],
      "formAdvantage": false,
      "odds": null,
      "forebet": null,
      "sofascore": null,
      "focusTeam": "home"
    },
    {
      "id": -558018692605326601,
      "homeTeam": "Carreno-Busta P.",
      "awayTeam": "Bennani R.",
      "time": "",
      "date": "2026-02-14",
      "league": "",
      "country": "",
      "sport": "tennis",
      "matchUrl": "",
      "qualifies": true,
      "h2h": {
        "home": 0,
        "draw": 0,
        "away": 0,
        "total": 0,
        "winRate": 0
      },
      "homeForm": [],
      "awayForm": [],
      "homeFormHome": [],
      "awayFormAway": [],
      "formAdvantage": false,
      "odds": null,
      "forebet": {
        "prediction": "2",
        "probability": 68.0,
        "exactScore": null,
        "overUnder": null,
        "btts": null
      },
      "sofascore": {
        "home": 91,
        "draw": null,
        "away": 9,
        "votes": 841
      },
      "focusTeam": "home"
    },
    {
      "id": -8554741224205983357,
      "homeTeam": "Trungelliti M.",
      "awayTeam": "Harris B.",
      "time": "",
      "date": "2026-02-14",
      "league": "",
      "country": "",
      "sport": "tennis",
      "matchUrl": "",
      "qualifies": false,
      "h2h": {
        "home": 0,
        "draw": 0,
        "away": 0,
        "total": 1,
        "winRate": 100
      },
      "homeForm": [
        "L",
        "L",
        "L",
        "L",
        "L"
      ],
      "awayForm": [
        "W",
        "W",
        "W",
        "W",
        "W"
      ],
      "homeFormHome": [],
      "awayFormAway": [],
      "formAdvantage": false,
      "odds": null,
      "forebet": null,
      "sofascore": null,
      "focusTeam": "home"
    },
    {
      "id": 7719871855861455287,
      "homeTeam": "Carballes Baena R.",
      "awayTeam": "O'Connell C.",
      "time": "",
      "date": "2026-02-14",
      "league": "",
      "country": "",
      "sport": "tennis",
      "matchUrl": "",
      "qualifies": true,
      "h2h": {
        "home": 1,
        "draw": 0,
        "away": 0,
        "total": 3,
        "winRate": 66
      },
      "homeForm": [
        "W",
        "L",
        "L",
        "L",
        "L"
      ],
      "awayForm": [
        "L",
        "W",
        "W",
        "W",
        "W"
      ],
      "homeFormHome": [],
      "awayFormAway": [],
      "formAdvantage": false,
      "odds": null,
      "forebet": {
        "prediction": "1",
        "probability": 61.0,
        "exactScore": null,
        "overUnder": null,
        "btts": null
      },
      "sofascore": {
        "home": 22,
        "draw": null,
        "away": 78,
        "votes": 874
      },
      "focusTeam": "home"
    },
    {
      "id": 45979573109186402,
      "homeTeam": "Faria J.",
      "awayTeam": "Jarry N.",
      "time": "",
      "date": "2026-02-14",
      "league": "",
      "country": "",
      "sport": "tennis",
      "matchUrl": "",
      "qualifies": false,
      "h2h": {
        "home": 0,
        "draw": 0,
        "away": 0,
        "total": 0,
        "winRate": 0
      },
      "homeForm": [],
      "awayForm": [],
      "homeFormHome": [],
      "awayFormAway": [],
      "formAdvantage": false,
      "odds": null,
      "forebet": null,
      "sofascore": null,
      "focusTeam": "home"
    },
    {
      "id": 4639033223464293501,
      "homeTeam": "Moller E.",
      "awayTeam": "Passaro F.",
      "time": "",
      "date": "2026-02-14",
      "league": "",
      "country": "",
      "sport": "tennis",
      "matchUrl": "",
      "qualifies": true,
      "h2h": {
        "home": 0,
        "draw": 0,
        "away": 0,
        "total": 0,
        "winRate": 0
      },
      "homeForm": [],
      "awayForm": [],
      "homeFormHome": [],
      "awayFormAway": [],
      "formAdvantage": false,
      "odds": null,
      "forebet": {
        "prediction": "2",
        "probability": 71.0,
        "exactScore": null,
        "overUnder": null,
        "btts": null
      },
      "sofascore": {
        "home": 59,
        "draw": null,
        "away": 41,
        "votes": 231
      },
      "focusTeam": "home"
    },
    {
      "id": 2468633240684390135,
      "homeTeam": "Pellegrino A.",
      "awayTeam": "Gaubas V.",
      "time": "",
      "date": "2026-02-14",
      "league": "",
      "country": "",
      "sport": "tennis",
      "matchUrl": "",
      "qualifies": false,
      "h2h": {
        "home": 1,
        "draw": 0,
        "away": 0,
        "total": 3,
        "winRate": 66
      },
      "homeForm": [
        "L",
        "W",
        "L",
        "L",
        "L"
      ],
      "awayForm": [
        "W",
        "L",
        "W",
        "W",
        "W"
      ],
      "homeFormHome": [],
      "awayFormAway": [],
      "formAdvantage": false,
      "odds": null,
      "forebet": null,
      "sofascore": null,
      "focusTeam": "home"
    },
    {
      "id": -197338616798748000,
      "homeTeam": "Tseng C. H.",
      "awayTeam": "Marcondes I.",
      "time": "",
      "date": "2026-02-14",
      "league": "",
      "country": "",
      "sport": "tennis",
      "matchUrl": "",
      "qualifies": true,
      "h2h": {
        "home": 0,
        "draw": 0,
        "away": 0,
        "total": 0,
        "winRate": 0
      },
      "homeForm": [],
      "awayForm": [],
      "homeFormHome": [],
      "awayFormAway": [],
      "formAdvantage": false,
      "odds": null,
      "forebet": {
        "prediction": "1",
        "probability": 78.0,
        "exactScore": null,
        "overUnder": null,
        "btts": null
      },
      "sofascore": {
        "home": 86,
        "draw": null,
        "away": 14,
        "votes": 244
      },
      "focusTeam": "home"
    },
    {
      "id": -2177421820311195580,
      "homeTeam": "Barrios Vera T.",
      "awayTeam": "Boscardin Dias P.",
      "time": "",
      "date": "2026-02-14",
      "league": "",
      "country": "",
      "sport": "tennis",
      "matchUrl": "",
      "qualifies": false,
      "h2h": {
        "home": 0,
        "draw": 0,
        "away": 0,
        "total": 1,
        "winRate": 100
      },
      "homeForm": [
        "L",
        "L",
        "L",
        "L",
        "L"
      ],
      "awayForm": [
        "W",
        "W",
        "W",
        "W",
        "W"
      ],
      "homeFormHome": [],
      "awayFormAway": [],
      "formAdvantage": false,
      "odds": null,
      "forebet": null,
      "sofascore": null,
      "focusTeam": "home"
    },
    {
      "id": 4223806300380201727,
      "homeTeam": "Dellien H.",
      "awayTeam": "Lajovic D.",
      "time": "",
      "date": "2026-02-14",
      "league": "",
      "country": "",
      "sport": "tennis",
      "matchUrl": "",
      "qualifies": true,
      "h2h": {
        "home": 0,
        "draw": 0,
        "away": 0,
        "total": 0,
        "winRate": 0
      },
      "homeForm": [],
      "awayForm": [],
      "homeFormHome": [],
      "awayFormAway": [],
      "formAdvantage": false,
      "odds": null,
      "forebet": {
        "prediction": "2",
        "probability": 52.0,
        "exactScore": null,
        "overUnder": null,
        "btts": null
      },
      "sofascore": {
        "home": 40,
        "draw": null,
        "away": 60,
        "votes": 213
      },
      "focusTeam": "home"
    },
    {
      "id": -2746418871710555022,
      "homeTeam": "Galan D. E.",
      "awayTeam": "Prizmic D.",
      "time": "",
      "date": "2026-02-14",
      "league": "",
      "country": "",
      "sport": "tennis",
      "matchUrl": "",
      "qualifies": true,
      "h2h": {
        "home": 0,
        "draw": 0,
        "away": 0,
        "total": 0,
        "winRate": 0
      },
      "homeForm": [],
      "awayForm": [],
      "homeFormHome": [],
      "awayFormAway": [],
      "formAdvantage": false,
      "odds": null,
      "forebet": {
        "prediction": "1",
        "probability": 66.0,
        "exactScore": null,
        "overUnder": null,
        "btts": null
      },
      "sofascore": {
        "home": 18,
        "draw": null,
        "away": 82,
        "votes": 241
      },
      "focusTeam": "home"
    },
    {
      "id": 4738031554414028107,
      "homeTeam": "Vallejo D.",
      "awayTeam": "Monteiro T.",
      "time": "",
      "date": "2026-02-14",
      "league": "",
      "country": "",
      "sport": "tennis",
      "matchUrl": "",
      "qualifies": true,
      "h2h": {
        "home": 1,
        "draw": 0,
        "away": 0,
        "total": 1,
        "winRate": 100
      },
      "homeForm": [
        "W",
        "W",
        "W",
        "W",
        "W"
      ],
      "awayForm": [
        "L",
        "L",
        "L",
        "L",
        "L"
      ],
      "homeFormHome": [],
      "awayFormAway": [],
      "formAdvantage": false,
      "odds": null,
      "forebet": {
        "prediction": "1",
        "probability": 59.0,
        "exactScore": null,
        "overUnder": null,
        "btts": null
      },
      "sofascore": {
        "home": 72,
        "draw": null,
        "away": 28,
        "votes": 289
      },
      "focusTeam": "home"
    },
    {
      "id": 8859851314013096892,
      "homeTeam": "Muchova K.",
      "awayTeam": "Mboko V.",
      "time": "",
      "date": "2026-02-14",
      "league": "",
      "country": "",
      "sport": "tennis",
      "matchUrl": "",
      "qualifies": false,
      "h2h": {
        "home": 0,
        "draw": 0,
        "away": 0,
        "total": 0,
        "winRate": 0
      },
      "homeForm": [],
      "awayForm": [],
      "homeFormHome": [],
      "awayFormAway": [],
      "formAdvantage": false,
      "odds": null,
      "forebet": null,
      "sofascore": null,
      "focusTeam": "home"
    },
    {
      "id": 3432853687553791284,
      "homeTeam": "Baptiste H.",
      "awayTeam": "Sramkova R.",
      "time": "",
      "date": "2026-02-14",
      "league": "",
      "country": "",
      "sport": "tennis",
      "matchUrl": "",
      "qualifies": true,
      "h2h": {
        "home": 1,
        "draw": 0,
        "away": 0,
        "total": 1,
        "winRate": 100
      },
      "homeForm": [
        "W",
        "W",
        "W",
        "W",
        "W"
      ],
      "awayForm": [
        "L",
        "L",
        "L",
        "L",
        "L"
      ],
      "homeFormHome": [],
      "awayFormAway": [],
      "formAdvantage": false,
      "odds": null,
      "forebet": {
        "prediction": "1",
        "probability": 71.0,
        "exactScore": null,
        "overUnder": null,
        "btts": null
      },
      "sofascore": {
        "home": 87,
        "draw": null,
        "away": 13,
        "votes": 2219
      },
      "focusTeam": "home"
    },
    {
      "id": -4568974514254223312,
      "homeTeam": "Erjavec V.",
      "awayTeam": "Uchijima M.",
      "time": "",
      "date": "2026-02-14",
      "league": "",
      "country": "",
      "sport": "tennis",
      "matchUrl": "",
      "qualifies": true,
      "h2h": {
        "home": 0,
        "draw": 0,
        "away": 0,
        "total": 1,
        "winRate": 100
      },
      "homeForm": [
        "L",
        "L",
        "L",
        "L",
        "L"
      ],
      "awayForm": [
        "W",
        "W",
        "W",
        "W",
        "W"
      ],
      "homeFormHome": [],
      "awayFormAway": [],
      "formAdvantage": false,
      "odds": null,
      "forebet": {
        "prediction": "1",
        "probability": 59.0,
        "exactScore": null,
        "overUnder": null,
        "btts": null
      },
      "sofascore": {
        "home": 17,
        "draw": null,
        "away": 83,
        "votes": 1485
      },
      "focusTeam": "home"
    },
    {
      "id": 8907254747976268462,
      "homeTeam": "Rachimowa K.",
      "awayTeam": "Seidel E.",
      "time": "",
      "date": "2026-02-14",
      "league": "",
      "country": "",
      "sport": "tennis",
      "matchUrl": "",
      "qualifies": false,
      "h2h": {
        "home": 0,
        "draw": 0,
        "away": 0,
        "total": 0,
        "winRate": 0
      },
      "homeForm": [],
      "awayForm": [],
      "homeFormHome": [],
      "awayFormAway": [],
      "formAdvantage": false,
      "odds": null,
      "forebet": null,
      "sofascore": null,
      "focusTeam": "home"
    },
    {
      "id": -5737066394339962392,
      "homeTeam": "Birrell K.",
      "awayTeam": "Volynets K.",
      "time": "",
      "date": "2026-02-14",
      "league": "",
      "country": "",
      "sport": "tennis",
      "matchUrl": "",
      "qualifies": false,
      "h2h": {
        "home": 1,
        "draw": 0,
        "away": 0,
        "total": 2,
        "winRate": 50
      },
      "homeForm": [
        "L",
        "W",
        "L",
        "L",
        "L"
      ],
      "awayForm": [
        "W",
        "L",
        "L",
        "L",
        "L"
      ],
      "homeFormHome": [],
      "awayFormAway": [],
      "formAdvantage": false,
      "odds": null,
      "forebet": null,
      "sofascore": null,
      "focusTeam": "home"
    },
    {
      "id": 430445285945218298,
      "homeTeam": "Fręch M.",
      "awayTeam": "Graczowa W.",
      "time": "",
      "date": "2026-02-14",
      "league": "",
      "country": "",
      "sport": "tennis",
      "matchUrl": "",
      "qualifies": false,
      "h2h": {
        "home": 0,
        "draw": 0,
        "away": 0,
        "total": 1,
        "winRate": 100
      },
      "homeForm": [
        "L",
        "L",
        "L",
        "L",
        "L"
      ],
      "awayForm": [
        "W",
        "W",
        "W",
        "W",
        "W"
      ],
      "homeFormHome": [],
      "awayFormAway": [],
      "formAdvantage": false,
      "odds": null,
      "forebet": null,
      "sofascore": null,
      "focusTeam": "home"
    },
    {
      "id": -5171345198939127478,
      "homeTeam": "Stearns P.",
      "awayTeam": "Ruse G.",
      "time": "",
      "date": "2026-02-14",
      "league": "",
      "country": "",
      "sport": "tennis",
      "matchUrl": "",
      "qualifies": false,
      "h2h": {
        "home": 0,
        "draw": 0,
        "away": 0,
        "total": 0,
        "winRate": 0
      },
      "homeForm": [],
      "awayForm": [],
      "homeFormHome": [],
      "awayFormAway": [],
      "formAdvantage": false,
      "odds": null,
      "forebet": null,
      "sofascore": null,
      "focusTeam": "home"
    },
    {
      "id": 2733411291655204540,
      "homeTeam": "Cocciaretto E.",
      "awayTeam": "Zacharowa A.",
      "time": "",
      "date": "2026-02-14",
      "league": "",
      "country": "",
      "sport": "tennis",
      "matchUrl": "",
      "qualifies": true,
      "h2h": {
        "home": 0,
        "draw": 0,
        "away": 0,
        "total": 0,
        "winRate": 0
      },
      "homeForm": [],
      "awayForm": [],
      "homeFormHome": [],
      "awayFormAway": [],
      "formAdvantage": false,
      "odds": null,
      "forebet": {
        "prediction": "2",
        "probability": 71.0,
        "exactScore": null,
        "overUnder": null,
        "btts": null
      },
      "sofascore": {
        "home": 86,
        "draw": null,
        "away": 14,
        "votes": 1598
      },
      "focusTeam": "home"
    },
    {
      "id": 6451852313913261893,
      "homeTeam": "Kartal S.",
      "awayTeam": "Sasnowicz A.",
      "time": "",
      "date": "2026-02-14",
      "league": "",
      "country": "",
      "sport": "tennis",
      "matchUrl": "",
      "qualifies": true,
      "h2h": {
        "home": 1,
        "draw": 0,
        "away": 0,
        "total": 1,
        "winRate": 100
      },
      "homeForm": [
        "W",
        "W",
        "W",
        "W",
        "W"
      ],
      "awayForm": [
        "L",
        "L",
        "L",
        "L",
        "L"
      ],
      "homeFormHome": [],
      "awayFormAway": [],
      "formAdvantage": false,
      "odds": null,
      "forebet": {
        "prediction": "2",
        "probability": 58.0,
        "exactScore": null,
        "overUnder": null,
        "btts": null
      },
      "sofascore": {
        "home": 84,
        "draw": null,
        "away": 16,
        "votes": 1318
      },
      "focusTeam": "home"
    },
    {
      "id": 4132897466319546771,
      "homeTeam": null,
      "awayTeam": null,
      "time": "",
      "date": "2026-02-14",
      "league": "",
      "country": "",
      "sport": "tennis",
      "matchUrl": "",
      "qualifies": false,
      "h2h": {
        "home": 0,
        "draw": 0,
        "away": 0,
        "total": 5,
        "winRate": 0
      },
      "homeForm": [],
      "awayForm": [],
      "homeFormHome": [],
      "awayFormAway": [],
      "formAdvantage": false,
      "odds": null,
      "forebet": null,
      "sofascore": null,
      "focusTeam": "home"
    },
    {
      "id": 4132897466319546771,
      "homeTeam": null,
      "awayTeam": null,
      "time": "",
      "date": "2026-02-14",
      "league": "",
      "country": "",
      "sport": "tennis",
      "matchUrl": "",
      "qualifies": false,
      "h2h": {
        "home": 0,
        "draw": 0,
        "away": 0,
        "total": 5,
        "winRate": 0
      },
      "homeForm": [],
      "awayForm": [],
      "homeFormHome": [],
      "awayFormAway": [],
      "formAdvantage": false,
      "odds": null,
      "forebet": null,
      "sofascore": null,
      "focusTeam": "home"
    },
    {
      "id": 4132897466319546771,
      "homeTeam": null,
      "awayTeam": null,
      "time": "",
      "date": "2026-02-14",
      "league": "",
      "country": "",
      "sport": "tennis",
      "matchUrl": "",
      "qualifies": false,
      "h2h": {
        "home": 0,
        "draw": 0,
        "away": 0,
        "total": 5,
        "winRate": 0
      },
      "homeForm": [],
      "awayForm": [],
      "homeFormHome": [],
      "awayFormAway": [],
      "formAdvantage": false,
      "odds": null,
      "forebet": null,
      "sofascore": null,
      "focusTeam": "home"
    },
    {
      "id": 4132897466319546771,
      "homeTeam": null,
      "awayTeam": null,
      "time": "",
      "date": "2026-02-14",
      "league": "",
      "country": "",
      "sport": "tennis",
      "matchUrl": "",
      "qualifies": false,
      "h2h": {
        "home": 0,
        "draw": 0,
        "away": 0,
        "total": 5,
        "winRate": 0
      },
      "homeForm": [],
      "awayForm": [],
      "homeFormHome": [],
      "awayFormAway": [],
      "formAdvantage": false,
      "odds": null,
      "forebet": null,
      "sofascore": null,
      "focusTeam": "home"
    },
    {
      "id": 4132897466319546771,
      "homeTeam": null,
      "awayTeam": null,
      "time": "",
      "date": "2026-02-14",
      "league": "",
      "country": "",
      "sport": "tennis",
      "matchUrl": "",
      "qualifies": false,
      "h2h": {
        "home": 0,
        "draw": 0,
        "away": 0,
        "total": 5,
        "winRate": 0
      },
      "homeForm": [],
      "awayForm": [],
      "homeFormHome": [],
      "awayFormAway": [],
      "formAdvantage": false,
      "odds": null,
      "forebet": null,
      "sofascore": null,
      "focusTeam": "home"
    },
    {
      "id": 4132897466319546771,
      "homeTeam": null,
      "awayTeam": null,
      "time": "",
      "date": "2026-02-14",
      "league": "",
      "country": "",
      "sport": "tennis",
      "matchUrl": "",
      "qualifies": false,
      "h2h": {
        "home": 0,
        "draw": 0,
        "away": 0,
        "total": 5,
        "winRate": 0
      },
      "homeForm": [],
      "awayForm": [],
      "homeFormHome": [],
      "awayFormAway": [],
      "formAdvantage": false,
      "odds": null,
      "forebet": null,
      "sofascore": null,
      "focusTeam": "home"
    },
    {
      "id": 832420438099122078,
      "homeTeam": "Dostanic S.",
      "awayTeam": "Andrade A.",
      "time": "",
      "date": "2026-02-14",
      "league": "",
      "country": "",
      "sport": "tennis",
      "matchUrl": "",
      "qualifies": true,
      "h2h": {
        "home": 0,
        "draw": 0,
        "away": 0,
        "total": 0,
        "winRate": 0
      },
      "homeForm": [],
      "awayForm": [],
      "homeFormHome": [],
      "awayFormAway": [],
      "formAdvantage": false,
      "odds": null,
      "forebet": {
        "prediction": "1",
        "probability": 53.0,
        "exactScore": null,
        "overUnder": null,
        "btts": null
      },
      "sofascore": {
        "home": 44,
        "draw": null,
        "away": 56,
        "votes": 244
      },
      "focusTeam": "home"
    },
    {
      "id": 7616053706402017193,
      "homeTeam": "Galarneau A.",
      "awayTeam": "Ilagan A.",
      "time": "",
      "date": "2026-02-14",
      "league": "",
      "country": "",
      "sport": "tennis",
      "matchUrl": "",
      "qualifies": true,
      "h2h": {
        "home": 0,
        "draw": 0,
        "away": 0,
        "total": 0,
        "winRate": 0
      },
      "homeForm": [],
      "awayForm": [],
      "homeFormHome": [],
      "awayFormAway": [],
      "formAdvantage": false,
      "odds": null,
      "forebet": {
        "prediction": "1",
        "probability": 56.0,
        "exactScore": null,
        "overUnder": null,
        "btts": null
      },
      "sofascore": {
        "home": 91,
        "draw": null,
        "away": 9,
        "votes": 219
      },
      "focusTeam": "home"
    },
    {
      "id": -4815163787456851628,
      "homeTeam": "Bolt A.",
      "awayTeam": "Moriya H.",
      "time": "",
      "date": "2026-02-14",
      "league": "",
      "country": "",
      "sport": "tennis",
      "matchUrl": "",
      "qualifies": true,
      "h2h": {
        "home": 5,
        "draw": 0,
        "away": 0,
        "total": 5,
        "winRate": 100
      },
      "homeForm": [
        "W",
        "W",
        "W",
        "W",
        "W"
      ],
      "awayForm": [
        "L",
        "L",
        "L",
        "L",
        "L"
      ],
      "homeFormHome": [],
      "awayFormAway": [],
      "formAdvantage": false,
      "odds": null,
      "forebet": {
        "prediction": "2",
        "probability": 53.0,
        "exactScore": null,
        "overUnder": null,
        "btts": null
      },
      "sofascore": {
        "home": 90,
        "draw": null,
        "away": 10,
        "votes": 854
      },
      "focusTeam": "home"
    },
    {
      "id": -5954371650003021857,
      "homeTeam": "Zhang Z.",
      "awayTeam": "Sakamoto R.",
      "time": "",
      "date": "2026-02-14",
      "league": "",
      "country": "",
      "sport": "tennis",
      "matchUrl": "",
      "qualifies": true,
      "h2h": {
        "home": 0,
        "draw": 0,
        "away": 0,
        "total": 0,
        "winRate": 0
      },
      "homeForm": [],
      "awayForm": [],
      "homeFormHome": [],
      "awayFormAway": [],
      "formAdvantage": false,
      "odds": null,
      "forebet": {
        "prediction": "2",
        "probability": 60.0,
        "exactScore": null,
        "overUnder": null,
        "btts": null
      },
      "sofascore": {
        "home": 54,
        "draw": null,
        "away": 46,
        "votes": 1140
      },
      "focusTeam": "home"
    },
    {
      "id": 7438595597806707511,
      "homeTeam": "Kaśnikowski M.",
      "awayTeam": "Gomez F. A.",
      "time": "",
      "date": "2026-02-14",
      "league": "",
      "country": "",
      "sport": "tennis",
      "matchUrl": "",
      "qualifies": true,
      "h2h": {
        "home": 0,
        "draw": 0,
        "away": 0,
        "total": 0,
        "winRate": 0
      },
      "homeForm": [],
      "awayForm": [],
      "homeFormHome": [],
      "awayFormAway": [],
      "formAdvantage": false,
      "odds": null,
      "forebet": {
        "prediction": "2",
        "probability": 61.0,
        "exactScore": null,
        "overUnder": null,
        "btts": null
      },
      "sofascore": {
        "home": 20,
        "draw": null,
        "away": 80,
        "votes": 779
      },
      "focusTeam": "home"
    },
    {
      "id": -4392289167983749636,
      "homeTeam": "Ferreira Silva F.",
      "awayTeam": "Simakin I.",
      "time": "",
      "date": "2026-02-14",
      "league": "",
      "country": "",
      "sport": "tennis",
      "matchUrl": "",
      "qualifies": false,
      "h2h": {
        "home": 1,
        "draw": 0,
        "away": 0,
        "total": 1,
        "winRate": 100
      },
      "homeForm": [
        "W",
        "W",
        "W",
        "W",
        "W"
      ],
      "awayForm": [
        "L",
        "L",
        "L",
        "L",
        "L"
      ],
      "homeFormHome": [],
      "awayFormAway": [],
      "formAdvantage": false,
      "odds": null,
      "forebet": null,
      "sofascore": null,
      "focusTeam": "home"
    },
    {
      "id": 8792575813010585772,
      "homeTeam": "Collignon R.",
      "awayTeam": "Tabur C.",
      "time": "",
      "date": "2026-02-14",
      "league": "",
      "country": "",
      "sport": "tennis",
      "matchUrl": "",
      "qualifies": true,
      "h2h": {
        "home": 1,
        "draw": 0,
        "away": 0,
        "total": 1,
        "winRate": 100
      },
      "homeForm": [
        "W",
        "W",
        "W",
        "W",
        "W"
      ],
      "awayForm": [
        "L",
        "L",
        "L",
        "L",
        "L"
      ],
      "homeFormHome": [],
      "awayFormAway": [],
      "formAdvantage": false,
      "odds": null,
      "forebet": {
        "prediction": "1",
        "probability": 59.0,
        "exactScore": null,
        "overUnder": null,
        "btts": null
      },
      "sofascore": {
        "home": 89,
        "draw": null,
        "away": 11,
        "votes": 592
      },
      "focusTeam": "home"
    },
    {
      "id": 5017895389273562933,
      "homeTeam": "Bonzi B.",
      "awayTeam": "Squire H.",
      "time": "",
      "date": "2026-02-14",
      "league": "",
      "country": "",
      "sport": "tennis",
      "matchUrl": "",
      "qualifies": true,
      "h2h": {
        "home": 1,
        "draw": 0,
        "away": 0,
        "total": 1,
        "winRate": 100
      },
      "homeForm": [
        "W",
        "W",
        "W",
        "W",
        "W"
      ],
      "awayForm": [
        "L",
        "L",
        "L",
        "L",
        "L"
      ],
      "homeFormHome": [],
      "awayFormAway": [],
      "formAdvantage": false,
      "odds": null,
      "forebet": {
        "prediction": "2",
        "probability": 57.0,
        "exactScore": null,
        "overUnder": null,
        "btts": null
      },
      "sofascore": {
        "home": 83,
        "draw": null,
        "away": 17,
        "votes": 218
      },
      "focusTeam": "home"
    },
    {
      "id": 798201302797617168,
      "homeTeam": "Llamas Ruiz P.",
      "awayTeam": "Harris L.",
      "time": "",
      "date": "2026-02-14",
      "league": "",
      "country": "",
      "sport": "tennis",
      "matchUrl": "",
      "qualifies": false,
      "h2h": {
        "home": 0,
        "draw": 0,
        "away": 0,
        "total": 0,
        "winRate": 0
      },
      "homeForm": [],
      "awayForm": [],
      "homeFormHome": [],
      "awayFormAway": [],
      "formAdvantage": false,
      "odds": null,
      "forebet": null,
      "sofascore": null,
      "focusTeam": "home"
    },
    {
      "id": 6478139662999811437,
      "homeTeam": "Merida Aguilar D.",
      "awayTeam": "Moro Canas A.",
      "time": "",
      "date": "2026-02-14",
      "league": "",
      "country": "",
      "sport": "tennis",
      "matchUrl": "",
      "qualifies": false,
      "h2h": {
        "home": 1,
        "draw": 0,
        "away": 0,
        "total": 2,
        "winRate": 50
      },
      "homeForm": [
        "W",
        "L",
        "L",
        "L",
        "L"
      ],
      "awayForm": [
        "L",
        "W",
        "L",
        "L",
        "L"
      ],
      "homeFormHome": [],
      "awayFormAway": [],
      "formAdvantage": false,
      "odds": null,
      "forebet": null,
      "sofascore": null,
      "focusTeam": "home"
    },
    {
      "id": -5837240075713594863,
      "homeTeam": "Chwalińska M.",
      "awayTeam": "Vidmanova D.",
      "time": "",
      "date": "2026-02-14",
      "league": "",
      "country": "",
      "sport": "tennis",
      "matchUrl": "",
      "qualifies": false,
      "h2h": {
        "home": 1,
        "draw": 0,
        "away": 0,
        "total": 1,
        "winRate": 100
      },
      "homeForm": [
        "W",
        "W",
        "W",
        "W",
        "W"
      ],
      "awayForm": [
        "L",
        "L",
        "L",
        "L",
        "L"
      ],
      "homeFormHome": [],
      "awayFormAway": [],
      "formAdvantage": false,
      "odds": null,
      "forebet": null,
      "sofascore": null,
      "focusTeam": "home"
    },
    {
      "id": -8539427468986340477,
      "homeTeam": "Jorge M.",
      "awayTeam": "Korneeva A.",
      "time": "",
      "date": "2026-02-14",
      "league": "",
      "country": "",
      "sport": "tennis",
      "matchUrl": "",
      "qualifies": true,
      "h2h": {
        "home": 0,
        "draw": 0,
        "away": 0,
        "total": 0,
        "winRate": 0
      },
      "homeForm": [],
      "awayForm": [],
      "homeFormHome": [],
      "awayFormAway": [],
      "formAdvantage": false,
      "odds": null,
      "forebet": {
        "prediction": "2",
        "probability": 57.0,
        "exactScore": null,
        "overUnder": null,
        "btts": null
      },
      "sofascore": {
        "home": 26,
        "draw": null,
        "away": 74,
        "votes": 385
      },
      "focusTeam": "home"
    },
    {
      "id": 4132897466319546771,
      "homeTeam": null,
      "awayTeam": null,
      "time": "",
      "date": "2026-02-14",
      "league": "",
      "country": "",
      "sport": "tennis",
      "matchUrl": "",
      "qualifies": false,
      "h2h": {
        "home": 0,
        "draw": 0,
        "away": 0,
        "total": 5,
        "winRate": 0
      },
      "homeForm": [],
      "awayForm": [],
      "homeFormHome": [],
      "awayFormAway": [],
      "formAdvantage": false,
      "odds": null,
      "forebet": null,
      "sofascore": null,
      "focusTeam": "home"
    },
    {
      "id": 4132897466319546771,
      "homeTeam": null,
      "awayTeam": null,
      "time": "",
      "date": "2026-02-14",
      "league": "",
      "country": "",
      "sport": "tennis",
      "matchUrl": "",
      "qualifies": false,
      "h2h": {
        "home": 0,
        "draw": 0,
        "away": 0,
        "total": 5,
        "winRate": 0
      },
      "homeForm": [],
      "awayForm": [],
      "homeFormHome": [],
      "awayFormAway": [],
      "formAdvantage": false,
      "odds": null,
      "forebet": null,
      "sofascore": null,
      "focusTeam": "home"
    },
    {
      "id": 4132897466319546771,
      "homeTeam": null,
      "awayTeam": null,
      "time": "",
      "date": "2026-02-14",
      "league": "",
      "country": "",
      "sport": "tennis",
      "matchUrl": "",
      "qualifies": false,
      "h2h": {
        "home": 0,
        "draw": 0,
        "away": 0,
        "total": 5,
        "winRate": 0
      },
      "homeForm": [],
      "awayForm": [],
      "homeFormHome": [],
      "awayFormAway": [],
      "formAdvantage": false,
      "odds": null,
      "forebet": null,
      "sofascore": null,
      "focusTeam": "home"
    },
    {
      "id": 4132897466319546771,
      "homeTeam": null,
      "awayTeam": null,
      "time": "",
      "date": "2026-02-14",
      "league": "",
      "country": "",
      "sport": "tennis",
      "matchUrl": "",
      "qualifies": false,
      "h2h": {
        "home": 0,
        "draw": 0,
        "away": 0,
        "total": 5,
        "winRate": 0
      },
      "homeForm": [],
      "awayForm": [],
      "homeFormHome": [],
      "awayFormAway": [],
      "formAdvantage": false,
      "odds": null,
      "forebet": null,
      "sofascore": null,
      "focusTeam": "home"
    },
    {
      "id": 4132897466319546771,
      "homeTeam": null,
      "awayTeam": null,
      "time": "",
      "date": "2026-02-14",
      "league": "",
      "country": "",
      "sport": "tennis",
      "matchUrl": "",
      "qualifies": false,
      "h2h": {
        "home": 0,
        "draw": 0,
        "away": 0,
        "total": 5,
        "winRate": 0
      },
      "homeForm": [],
      "awayForm": [],
      "homeFormHome": [],
      "awayFormAway": [],
      "formAdvantage": false,
      "odds": null,
      "forebet": null,
      "sofascore": null,
      "focusTeam": "home"
    },
    {
      "id": 4132897466319546771,
      "homeTeam": null,
      "awayTeam": null,
      "time": "",
      "date": "2026-02-14",
      "league": "",
      "country": "",
      "sport": "tennis",
      "matchUrl": "",
      "qualifies": false,
      "h2h": {
        "home": 0,
        "draw": 0,
        "away": 0,
        "total": 5,
        "winRate": 0
      },
      "homeForm": [],
      "awayForm": [],
      "homeFormHome": [],
      "awayFormAway": [],
      "formAdvantage": false,
      "odds": null,
      "forebet": null,
      "sofascore": null,
      "focusTeam": "home"
    },
    {
      "id": 4132897466319546771,
      "homeTeam": null,
      "awayTeam": null,
      "time": "",
      "date": "2026-02-14",
      "league": "",
      "country": "",
      "sport": "tennis",
      "matchUrl": "",
      "qualifies": false,
      "h2h": {
        "home": 0,
        "draw": 0,
        "away": 0,
        "total": 5,
        "winRate": 0
      },
      "homeForm": [],
      "awayForm": [],
      "homeFormHome": [],
      "awayFormAway": [],
      "formAdvantage": false,
      "odds": null,
      "forebet": null,
      "sofascore": null,
      "focusTeam": "home"
    },
    {
      "id": 7511447776221493628,
      "homeTeam": "Fuele M.",
      "awayTeam": "Juan Mano A.",
      "time": "",
      "date": "2026-02-14",
      "league": "",
      "country": "",
      "sport": "tennis",
      "matchUrl": "",
      "qualifies": true,
      "h2h": {
        "home": 0,
        "draw": 0,
        "away": 0,
        "total": 0,
        "winRate": 0
      },
      "homeForm": [],
      "awayForm": [],
      "homeFormHome": [],
      "awayFormAway": [],
      "formAdvantage": false,
      "odds": null,
      "forebet": {
        "prediction": "2",
        "probability": 57.0,
        "exactScore": null,
        "overUnder": null,
        "btts": null
      },
      "sofascore": {
        "home": 51,
        "draw": null,
        "away": 49,
        "votes": 73
      },
      "focusTeam": "home"
    },
    {
      "id": 2325957851596883154,
      "homeTeam": "Parisca I.",
      "awayTeam": "Perez Contri S.",
      "time": "",
      "date": "2026-02-14",
      "league": "",
      "country": "",
      "sport": "tennis",
      "matchUrl": "",
      "qualifies": false,
      "h2h": {
        "home": 2,
        "draw": 0,
        "away": 0,
        "total": 3,
        "winRate": 66
      },
      "homeForm": [
        "W",
        "L",
        "W",
        "W",
        "W"
      ],
      "awayForm": [
        "L",
        "W",
        "L",
        "L",
        "L"
      ],
      "homeFormHome": [],
      "awayFormAway": [],
      "formAdvantage": false,
      "odds": null,
      "forebet": null,
      "sofascore": null,
      "focusTeam": "home"
    },
    {
      "id": -1127816001478087341,
      "homeTeam": "Erel Y.",
      "awayTeam": "Tepmahc N.",
      "time": "",
      "date": "2026-02-14",
      "league": "",
      "country": "",
      "sport": "tennis",
      "matchUrl": "",
      "qualifies": true,
      "h2h": {
        "home": 1,
        "draw": 0,
        "away": 0,
        "total": 1,
        "winRate": 100
      },
      "homeForm": [
        "W",
        "W",
        "W",
        "W",
        "W"
      ],
      "awayForm": [
        "L",
        "L",
        "L",
        "L",
        "L"
      ],
      "homeFormHome": [],
      "awayFormAway": [],
      "formAdvantage": false,
      "odds": null,
      "forebet": {
        "prediction": "1",
        "probability": 52.0,
        "exactScore": null,
        "overUnder": null,
        "btts": null
      },
      "sofascore": {
        "home": 86,
        "draw": null,
        "away": 14,
        "votes": 96
      },
      "focusTeam": "home"
    },
    {
      "id": -3596641483047182537,
      "homeTeam": "Rapagnetta D.",
      "awayTeam": "Berkieta T.",
      "time": "",
      "date": "2026-02-14",
      "league": "",
      "country": "",
      "sport": "tennis",
      "matchUrl": "",
      "qualifies": true,
      "h2h": {
        "home": 0,
        "draw": 0,
        "away": 0,
        "total": 0,
        "winRate": 0
      },
      "homeForm": [],
      "awayForm": [],
      "homeFormHome": [],
      "awayFormAway": [],
      "formAdvantage": false,
      "odds": null,
      "forebet": {
        "prediction": "2",
        "probability": 53.0,
        "exactScore": null,
        "overUnder": null,
        "btts": null
      },
      "sofascore": {
        "home": 10,
        "draw": null,
        "away": 90,
        "votes": 121
      },
      "focusTeam": "home"
    },
    {
      "id": 8073793824939078465,
      "homeTeam": "Moeller M.",
      "awayTeam": "Napolitano S.",
      "time": "",
      "date": "2026-02-14",
      "league": "",
      "country": "",
      "sport": "tennis",
      "matchUrl": "",
      "qualifies": false,
      "h2h": {
        "home": 0,
        "draw": 0,
        "away": 0,
        "total": 0,
        "winRate": 0
      },
      "homeForm": [],
      "awayForm": [],
      "homeFormHome": [],
      "awayFormAway": [],
      "formAdvantage": false,
      "odds": null,
      "forebet": null,
      "sofascore": null,
      "focusTeam": "home"
    },
    {
      "id": 3037422590918223519,
      "homeTeam": "Jubb P.",
      "awayTeam": "Brunold M.",
      "time": "",
      "date": "2026-02-14",
      "league": "",
      "country": "",
      "sport": "tennis",
      "matchUrl": "",
      "qualifies": true,
      "h2h": {
        "home": 0,
        "draw": 0,
        "away": 0,
        "total": 0,
        "winRate": 0
      },
      "homeForm": [],
      "awayForm": [],
      "homeFormHome": [],
      "awayFormAway": [],
      "formAdvantage": false,
      "odds": null,
      "forebet": {
        "prediction": "1",
        "probability": 59.0,
        "exactScore": null,
        "overUnder": null,
        "btts": null
      },
      "sofascore": {
        "home": 64,
        "draw": null,
        "away": 36,
        "votes": 61
      },
      "focusTeam": "home"
    },
    {
      "id": 3255034567625093670,
      "homeTeam": "Faucon R.",
      "awayTeam": "Poljicak M.",
      "time": "",
      "date": "2026-02-14",
      "league": "",
      "country": "",
      "sport": "tennis",
      "matchUrl": "",
      "qualifies": true,
      "h2h": {
        "home": 0,
        "draw": 0,
        "away": 0,
        "total": 1,
        "winRate": 100
      },
      "homeForm": [
        "L",
        "L",
        "L",
        "L",
        "L"
      ],
      "awayForm": [
        "W",
        "W",
        "W",
        "W",
        "W"
      ],
      "homeFormHome": [],
      "awayFormAway": [],
      "formAdvantage": false,
      "odds": null,
      "forebet": {
        "prediction": "1",
        "probability": 78.0,
        "exactScore": null,
        "overUnder": null,
        "btts": null
      },
      "sofascore": {
        "home": 12,
        "draw": null,
        "away": 88,
        "votes": 109
      },
      "focusTeam": "home"
    },
    {
      "id": 6645241487444561164,
      "homeTeam": "Purtseladze S.",
      "awayTeam": "Tiurniew J.",
      "time": "",
      "date": "2026-02-14",
      "league": "",
      "country": "",
      "sport": "tennis",
      "matchUrl": "",
      "qualifies": false,
      "h2h": {
        "home": 2,
        "draw": 0,
        "away": 0,
        "total": 3,
        "winRate": 66
      },
      "homeForm": [
        "W",
        "W",
        "L",
        "W",
        "W"
      ],
      "awayForm": [
        "L",
        "L",
        "W",
        "L",
        "L"
      ],
      "homeFormHome": [],
      "awayFormAway": [],
      "formAdvantage": false,
      "odds": null,
      "forebet": null,
      "sofascore": null,
      "focusTeam": "home"
    },
    {
      "id": 2561290569811110084,
      "homeTeam": "Kuzuhara B.",
      "awayTeam": "Johnson A.",
      "time": "",
      "date": "2026-02-14",
      "league": "",
      "country": "",
      "sport": "tennis",
      "matchUrl": "",
      "qualifies": true,
      "h2h": {
        "home": 0,
        "draw": 0,
        "away": 0,
        "total": 0,
        "winRate": 0
      },
      "homeForm": [],
      "awayForm": [],
      "homeFormHome": [],
      "awayFormAway": [],
      "formAdvantage": false,
      "odds": null,
      "forebet": {
        "prediction": "2",
        "probability": 61.0,
        "exactScore": null,
        "overUnder": null,
        "btts": null
      },
      "sofascore": {
        "home": 60,
        "draw": null,
        "away": 40,
        "votes": 107
      },
      "focusTeam": "home"
    },
    {
      "id": -4383684396580753585,
      "homeTeam": "Monzon I.",
      "awayTeam": "Cazacu D. N.",
      "time": "",
      "date": "2026-02-14",
      "league": "",
      "country": "",
      "sport": "tennis",
      "matchUrl": "",
      "qualifies": true,
      "h2h": {
        "home": 0,
        "draw": 0,
        "away": 0,
        "total": 0,
        "winRate": 0
      },
      "homeForm": [],
      "awayForm": [],
      "homeFormHome": [],
      "awayFormAway": [],
      "formAdvantage": false,
      "odds": null,
      "forebet": {
        "prediction": "2",
        "probability": 52.0,
        "exactScore": null,
        "overUnder": null,
        "btts": null
      },
      "sofascore": {
        "home": 94,
        "draw": null,
        "away": 6,
        "votes": 231
      },
      "focusTeam": "home"
    },
    {
      "id": -8347598778504091821,
      "homeTeam": "Boitan G. A.",
      "awayTeam": "Chepelev A.",
      "time": "",
      "date": "2026-02-14",
      "league": "",
      "country": "",
      "sport": "tennis",
      "matchUrl": "",
      "qualifies": true,
      "h2h": {
        "home": 0,
        "draw": 0,
        "away": 0,
        "total": 0,
        "winRate": 0
      },
      "homeForm": [],
      "awayForm": [],
      "homeFormHome": [],
      "awayFormAway": [],
      "formAdvantage": false,
      "odds": null,
      "forebet": {
        "prediction": "2",
        "probability": 57.0,
        "exactScore": null,
        "overUnder": null,
        "btts": null
      },
      "sofascore": {
        "home": 71,
        "draw": null,
        "away": 29,
        "votes": 147
      },
      "focusTeam": "home"
    },
    {
      "id": -1415774776218302821,
      "homeTeam": "Pieri S.",
      "awayTeam": "Roca Batalla O.",
      "time": "",
      "date": "2026-02-14",
      "league": "",
      "country": "",
      "sport": "tennis",
      "matchUrl": "",
      "qualifies": true,
      "h2h": {
        "home": 0,
        "draw": 0,
        "away": 0,
        "total": 0,
        "winRate": 0
      },
      "homeForm": [],
      "awayForm": [],
      "homeFormHome": [],
      "awayFormAway": [],
      "formAdvantage": false,
      "odds": null,
      "forebet": {
        "prediction": "2",
        "probability": 58.0,
        "exactScore": null,
        "overUnder": null,
        "btts": null
      },
      "sofascore": {
        "home": 18,
        "draw": null,
        "away": 82,
        "votes": 120
      },
      "focusTeam": "home"
    },
    {
      "id": 3961247167221413463,
      "homeTeam": "Alcala Gurri M.",
      "awayTeam": "Martin A.",
      "time": "",
      "date": "2026-02-14",
      "league": "",
      "country": "",
      "sport": "tennis",
      "matchUrl": "",
      "qualifies": true,
      "h2h": {
        "home": 0,
        "draw": 0,
        "away": 0,
        "total": 0,
        "winRate": 0
      },
      "homeForm": [],
      "awayForm": [],
      "homeFormHome": [],
      "awayFormAway": [],
      "formAdvantage": false,
      "odds": null,
      "forebet": {
        "prediction": "2",
        "probability": 57.0,
        "exactScore": null,
        "overUnder": null,
        "btts": null
      },
      "sofascore": {
        "home": 53,
        "draw": null,
        "away": 47,
        "votes": 232
      },
      "focusTeam": "home"
    },
    {
      "id": 2632271159732141063,
      "homeTeam": "Van Der Meerschen M.",
      "awayTeam": "Santillan A.",
      "time": "",
      "date": "2026-02-14",
      "league": "",
      "country": "",
      "sport": "tennis",
      "matchUrl": "",
      "qualifies": true,
      "h2h": {
        "home": 0,
        "draw": 0,
        "away": 0,
        "total": 0,
        "winRate": 0
      },
      "homeForm": [],
      "awayForm": [],
      "homeFormHome": [],
      "awayFormAway": [],
      "formAdvantage": false,
      "odds": null,
      "forebet": {
        "prediction": "2",
        "probability": 57.0,
        "exactScore": null,
        "overUnder": null,
        "btts": null
      },
      "sofascore": {
        "home": 21,
        "draw": null,
        "away": 79,
        "votes": 103
      },
      "focusTeam": "home"
    },
    {
      "id": 631711487792888437,
      "homeTeam": "Coulibaly E.",
      "awayTeam": "Nikles J.",
      "time": "",
      "date": "2026-02-14",
      "league": "",
      "country": "",
      "sport": "tennis",
      "matchUrl": "",
      "qualifies": true,
      "h2h": {
        "home": 0,
        "draw": 0,
        "away": 0,
        "total": 0,
        "winRate": 0
      },
      "homeForm": [],
      "awayForm": [],
      "homeFormHome": [],
      "awayFormAway": [],
      "formAdvantage": false,
      "odds": null,
      "forebet": {
        "prediction": "1",
        "probability": 57.0,
        "exactScore": null,
        "overUnder": null,
        "btts": null
      },
      "sofascore": {
        "home": 83,
        "draw": null,
        "away": 17,
        "votes": 90
      },
      "focusTeam": "home"
    },
    {
      "id": -4720475038291926690,
      "homeTeam": "Kaouk M.",
      "awayTeam": "Faurel T.",
      "time": "",
      "date": "2026-02-14",
      "league": "",
      "country": "",
      "sport": "tennis",
      "matchUrl": "",
      "qualifies": true,
      "h2h": {
        "home": 0,
        "draw": 0,
        "away": 0,
        "total": 0,
        "winRate": 0
      },
      "homeForm": [],
      "awayForm": [],
      "homeFormHome": [],
      "awayFormAway": [],
      "formAdvantage": false,
      "odds": null,
      "forebet": {
        "prediction": "2",
        "probability": 61.0,
        "exactScore": null,
        "overUnder": null,
        "btts": null
      },
      "sofascore": {
        "home": 15,
        "draw": null,
        "away": 85,
        "votes": 81
      },
      "focusTeam": "home"
    },
    {
      "id": -5056103025769587510,
      "homeTeam": "Soriano Barrera A.",
      "awayTeam": "Onclin G.",
      "time": "",
      "date": "2026-02-14",
      "league": "",
      "country": "",
      "sport": "tennis",
      "matchUrl": "",
      "qualifies": true,
      "h2h": {
        "home": 0,
        "draw": 0,
        "away": 0,
        "total": 2,
        "winRate": 100
      },
      "homeForm": [
        "L",
        "L",
        "L",
        "L",
        "L"
      ],
      "awayForm": [
        "W",
        "W",
        "W",
        "W",
        "W"
      ],
      "homeFormHome": [],
      "awayFormAway": [],
      "formAdvantage": false,
      "odds": null,
      "forebet": {
        "prediction": "1",
        "probability": 52.0,
        "exactScore": null,
        "overUnder": null,
        "btts": null
      },
      "sofascore": {
        "home": 16,
        "draw": null,
        "away": 84,
        "votes": 62
      },
      "focusTeam": "home"
    },
    {
      "id": -991847068828200042,
      "homeTeam": "Basing M.",
      "awayTeam": "Broady L.",
      "time": "",
      "date": "2026-02-14",
      "league": "",
      "country": "",
      "sport": "tennis",
      "matchUrl": "",
      "qualifies": true,
      "h2h": {
        "home": 0,
        "draw": 0,
        "away": 0,
        "total": 0,
        "winRate": 0
      },
      "homeForm": [],
      "awayForm": [],
      "homeFormHome": [],
      "awayFormAway": [],
      "formAdvantage": false,
      "odds": null,
      "forebet": {
        "prediction": "1",
        "probability": 65.0,
        "exactScore": null,
        "overUnder": null,
        "btts": null
      },
      "sofascore": {
        "home": 12,
        "draw": null,
        "away": 88,
        "votes": 85
      },
      "focusTeam": "home"
    },
    {
      "id": 8691976327445754680,
      "homeTeam": "Hrastar A.",
      "awayTeam": "Torner Sensano N.",
      "time": "",
      "date": "2026-02-14",
      "league": "",
      "country": "",
      "sport": "tennis",
      "matchUrl": "",
      "qualifies": true,
      "h2h": {
        "home": 0,
        "draw": 0,
        "away": 0,
        "total": 0,
        "winRate": 0
      },
      "homeForm": [],
      "awayForm": [],
      "homeFormHome": [],
      "awayFormAway": [],
      "formAdvantage": false,
      "odds": null,
      "forebet": {
        "prediction": "1",
        "probability": 53.0,
        "exactScore": null,
        "overUnder": null,
        "btts": null
      },
      "sofascore": {
        "home": 43,
        "draw": null,
        "away": 57,
        "votes": 56
      },
      "focusTeam": "home"
    },
    {
      "id": -4667409584844476103,
      "homeTeam": "Jialin T.",
      "awayTeam": "Garcia Cid Ma.",
      "time": "",
      "date": "2026-02-14",
      "league": "",
      "country": "",
      "sport": "tennis",
      "matchUrl": "",
      "qualifies": true,
      "h2h": {
        "home": 0,
        "draw": 0,
        "away": 0,
        "total": 0,
        "winRate": 0
      },
      "homeForm": [],
      "awayForm": [],
      "homeFormHome": [],
      "awayFormAway": [],
      "formAdvantage": false,
      "odds": null,
      "forebet": {
        "prediction": "2",
        "probability": 52.0,
        "exactScore": null,
        "overUnder": null,
        "btts": null
      },
      "sofascore": {
        "home": 68,
        "draw": null,
        "away": 32,
        "votes": 65
      },
      "focusTeam": "home"
    },
    {
      "id": 1954190983891062008,
      "homeTeam": "Falkowska W.",
      "awayTeam": "Sakellaridi S.",
      "time": "",
      "date": "2026-02-14",
      "league": "",
      "country": "",
      "sport": "tennis",
      "matchUrl": "",
      "qualifies": true,
      "h2h": {
        "home": 0,
        "draw": 0,
        "away": 0,
        "total": 1,
        "winRate": 100
      },
      "homeForm": [
        "L",
        "L",
        "L",
        "L",
        "L"
      ],
      "awayForm": [
        "W",
        "W",
        "W",
        "W",
        "W"
      ],
      "homeFormHome": [],
      "awayFormAway": [],
      "formAdvantage": false,
      "odds": null,
      "forebet": {
        "prediction": "1",
        "probability": 64.0,
        "exactScore": null,
        "overUnder": null,
        "btts": null
      },
      "sofascore": {
        "home": 57,
        "draw": null,
        "away": 43,
        "votes": 95
      },
      "focusTeam": "home"
    },
    {
      "id": -3841328549574090201,
      "homeTeam": "Ivanova I.",
      "awayTeam": "Maquet M.",
      "time": "",
      "date": "2026-02-14",
      "league": "",
      "country": "",
      "sport": "tennis",
      "matchUrl": "",
      "qualifies": true,
      "h2h": {
        "home": 0,
        "draw": 0,
        "away": 0,
        "total": 0,
        "winRate": 0
      },
      "homeForm": [],
      "awayForm": [],
      "homeFormHome": [],
      "awayFormAway": [],
      "formAdvantage": false,
      "odds": null,
      "forebet": {
        "prediction": "1",
        "probability": 59.0,
        "exactScore": null,
        "overUnder": null,
        "btts": null
      },
      "sofascore": {
        "home": 74,
        "draw": null,
        "away": 26,
        "votes": 81
      },
      "focusTeam": "home"
    },
    {
      "id": -4466265000795873502,
      "homeTeam": "Ren Y.",
      "awayTeam": "Alhussein L.",
      "time": "",
      "date": "2026-02-14",
      "league": "",
      "country": "",
      "sport": "tennis",
      "matchUrl": "",
      "qualifies": false,
      "h2h": {
        "home": 0,
        "draw": 0,
        "away": 0,
        "total": 0,
        "winRate": 0
      },
      "homeForm": [],
      "awayForm": [],
      "homeFormHome": [],
      "awayFormAway": [],
      "formAdvantage": false,
      "odds": null,
      "forebet": null,
      "sofascore": null,
      "focusTeam": "home"
    },
    {
      "id": -8796928928658647215,
      "homeTeam": "Samir S.",
      "awayTeam": "Kroitor K.",
      "time": "",
      "date": "2026-02-14",
      "league": "",
      "country": "",
      "sport": "tennis",
      "matchUrl": "",
      "qualifies": true,
      "h2h": {
        "home": 0,
        "draw": 0,
        "away": 0,
        "total": 0,
        "winRate": 0
      },
      "homeForm": [],
      "awayForm": [],
      "homeFormHome": [],
      "awayFormAway": [],
      "formAdvantage": false,
      "odds": null,
      "forebet": {
        "prediction": "1",
        "probability": 51.0,
        "exactScore": null,
        "overUnder": null,
        "btts": null
      },
      "sofascore": {
        "home": 59,
        "draw": null,
        "away": 41,
        "votes": 17
      },
      "focusTeam": "home"
    },
    {
      "id": -1540061898561016958,
      "homeTeam": "Brancaccio N.",
      "awayTeam": "Zantedeschi A.",
      "time": "",
      "date": "2026-02-14",
      "league": "",
      "country": "",
      "sport": "tennis",
      "matchUrl": "",
      "qualifies": true,
      "h2h": {
        "home": 2,
        "draw": 0,
        "away": 0,
        "total": 2,
        "winRate": 100
      },
      "homeForm": [
        "W",
        "W",
        "W",
        "W",
        "W"
      ],
      "awayForm": [
        "L",
        "L",
        "L",
        "L",
        "L"
      ],
      "homeFormHome": [],
      "awayFormAway": [],
      "formAdvantage": false,
      "odds": null,
      "forebet": {
        "prediction": "2",
        "probability": 53.0,
        "exactScore": null,
        "overUnder": null,
        "btts": null
      },
      "sofascore": {
        "home": 89,
        "draw": null,
        "away": 11,
        "votes": 120
      },
      "focusTeam": "home"
    },
    {
      "id": 3491834172774803273,
      "homeTeam": "Giovannini L.",
      "awayTeam": "Ruggeri J.",
      "time": "",
      "date": "2026-02-14",
      "league": "",
      "country": "",
      "sport": "tennis",
      "matchUrl": "",
      "qualifies": true,
      "h2h": {
        "home": 0,
        "draw": 0,
        "away": 0,
        "total": 0,
        "winRate": 0
      },
      "homeForm": [],
      "awayForm": [],
      "homeFormHome": [],
      "awayFormAway": [],
      "formAdvantage": false,
      "odds": null,
      "forebet": {
        "prediction": "1",
        "probability": 57.0,
        "exactScore": null,
        "overUnder": null,
        "btts": null
      },
      "sofascore": {
        "home": 78,
        "draw": null,
        "away": 22,
        "votes": 123
      },
      "focusTeam": "home"
    },
    {
      "id": -6513330461940681346,
      "homeTeam": "Hercog P.",
      "awayTeam": "Kotliar Y.",
      "time": "",
      "date": "2026-02-14",
      "league": "",
      "country": "",
      "sport": "tennis",
      "matchUrl": "",
      "qualifies": true,
      "h2h": {
        "home": 0,
        "draw": 0,
        "away": 0,
        "total": 0,
        "winRate": 0
      },
      "homeForm": [],
      "awayForm": [],
      "homeFormHome": [],
      "awayFormAway": [],
      "formAdvantage": false,
      "odds": null,
      "forebet": {
        "prediction": "2",
        "probability": 65.0,
        "exactScore": null,
        "overUnder": null,
        "btts": null
      },
      "sofascore": {
        "home": 87,
        "draw": null,
        "away": 13,
        "votes": 252
      },
      "focusTeam": "home"
    },
    {
      "id": 2506748370072738649,
      "homeTeam": "Shubladze A.",
      "awayTeam": "Zolotareva R.",
      "time": "",
      "date": "2026-02-14",
      "league": "",
      "country": "",
      "sport": "tennis",
      "matchUrl": "",
      "qualifies": true,
      "h2h": {
        "home": 0,
        "draw": 0,
        "away": 0,
        "total": 0,
        "winRate": 0
      },
      "homeForm": [],
      "awayForm": [],
      "homeFormHome": [],
      "awayFormAway": [],
      "formAdvantage": false,
      "odds": null,
      "forebet": {
        "prediction": "1",
        "probability": 59.0,
        "exactScore": null,
        "overUnder": null,
        "btts": null
      },
      "sofascore": {
        "home": 80,
        "draw": null,
        "away": 20,
        "votes": 115
      },
      "focusTeam": "home"
    },
    {
      "id": 5304541100250354253,
      "homeTeam": "Naef C.",
      "awayTeam": "Podrez V.",
      "time": "",
      "date": "2026-02-14",
      "league": "",
      "country": "",
      "sport": "tennis",
      "matchUrl": "",
      "qualifies": true,
      "h2h": {
        "home": 0,
        "draw": 0,
        "away": 0,
        "total": 0,
        "winRate": 0
      },
      "homeForm": [],
      "awayForm": [],
      "homeFormHome": [],
      "awayFormAway": [],
      "formAdvantage": false,
      "odds": null,
      "forebet": {
        "prediction": "1",
        "probability": 67.0,
        "exactScore": null,
        "overUnder": null,
        "btts": null
      },
      "sofascore": {
        "home": 70,
        "draw": null,
        "away": 30,
        "votes": 44
      },
      "focusTeam": "home"
    },
    {
      "id": 336985980929398085,
      "homeTeam": "Grant T. C.",
      "awayTeam": "Vandromme J.",
      "time": "",
      "date": "2026-02-14",
      "league": "",
      "country": "",
      "sport": "tennis",
      "matchUrl": "",
      "qualifies": true,
      "h2h": {
        "home": 1,
        "draw": 0,
        "away": 0,
        "total": 1,
        "winRate": 100
      },
      "homeForm": [
        "W",
        "W",
        "W",
        "W",
        "W"
      ],
      "awayForm": [
        "L",
        "L",
        "L",
        "L",
        "L"
      ],
      "homeFormHome": [],
      "awayFormAway": [],
      "formAdvantage": false,
      "odds": null,
      "forebet": {
        "prediction": "2",
        "probability": 52.0,
        "exactScore": null,
        "overUnder": null,
        "btts": null
      },
      "sofascore": {
        "home": 54,
        "draw": null,
        "away": 46,
        "votes": 69
      },
      "focusTeam": "home"
    },
    {
      "id": -2561228157273177946,
      "homeTeam": "Gibson T.",
      "awayTeam": "Jones E.",
      "time": "",
      "date": "2026-02-14",
      "league": "",
      "country": "",
      "sport": "tennis",
      "matchUrl": "",
      "qualifies": false,
      "h2h": {
        "home": 1,
        "draw": 0,
        "away": 0,
        "total": 3,
        "winRate": 66
      },
      "homeForm": [
        "L",
        "W",
        "L",
        "L",
        "L"
      ],
      "awayForm": [
        "W",
        "L",
        "W",
        "W",
        "W"
      ],
      "homeFormHome": [],
      "awayFormAway": [],
      "formAdvantage": false,
      "odds": null,
      "forebet": null,
      "sofascore": null,
      "focusTeam": "home"
    },
    {
      "id": -2436470458183742429,
      "homeTeam": "Zhu L.",
      "awayTeam": "Preston T.",
      "time": "",
      "date": "2026-02-14",
      "league": "",
      "country": "",
      "sport": "tennis",
      "matchUrl": "",
      "qualifies": false,
      "h2h": {
        "home": 1,
        "draw": 0,
        "away": 0,
        "total": 2,
        "winRate": 50
      },
      "homeForm": [
        "L",
        "W",
        "L",
        "L",
        "L"
      ],
      "awayForm": [
        "W",
        "L",
        "L",
        "L",
        "L"
      ],
      "homeFormHome": [],
      "awayFormAway": [],
      "formAdvantage": false,
      "odds": null,
      "forebet": null,
      "sofascore": null,
      "focusTeam": "home"
    },
    {
      "id": 190793950391508202,
      "homeTeam": "Kraus S.",
      "awayTeam": "Kovackova J.",
      "time": "",
      "date": "2026-02-14",
      "league": "",
      "country": "",
      "sport": "tennis",
      "matchUrl": "",
      "qualifies": true,
      "h2h": {
        "home": 0,
        "draw": 0,
        "away": 0,
        "total": 0,
        "winRate": 0
      },
      "homeForm": [],
      "awayForm": [],
      "homeFormHome": [],
      "awayFormAway": [],
      "formAdvantage": false,
      "odds": null,
      "forebet": {
        "prediction": "1",
        "probability": 51.0,
        "exactScore": null,
        "overUnder": null,
        "btts": null
      },
      "sofascore": {
        "home": 82,
        "draw": null,
        "away": 18,
        "votes": 122
      },
      "focusTeam": "home"
    },
    {
      "id": -8222675938452602081,
      "homeTeam": "Martincova T.",
      "awayTeam": "Siskova A.",
      "time": "",
      "date": "2026-02-14",
      "league": "",
      "country": "",
      "sport": "tennis",
      "matchUrl": "",
      "qualifies": false,
      "h2h": {
        "home": 1,
        "draw": 0,
        "away": 0,
        "total": 1,
        "winRate": 100
      },
      "homeForm": [
        "W",
        "W",
        "W",
        "W",
        "W"
      ],
      "awayForm": [
        "L",
        "L",
        "L",
        "L",
        "L"
      ],
      "homeFormHome": [],
      "awayFormAway": [],
      "formAdvantage": false,
      "odds": null,
      "forebet": null,
      "sofascore": null,
      "focusTeam": "home"
    },
    {
      "id": -8252782417648714822,
      "homeTeam": "Prozorova T.",
      "awayTeam": "Vandewinkel H.",
      "time": "",
      "date": "2026-02-14",
      "league": "",
      "country": "",
      "sport": "tennis",
      "matchUrl": "",
      "qualifies": false,
      "h2h": {
        "home": 1,
        "draw": 0,
        "away": 0,
        "total": 2,
        "winRate": 50
      },
      "homeForm": [
        "W",
        "L",
        "L",
        "L",
        "L"
      ],
      "awayForm": [
        "L",
        "W",
        "L",
        "L",
        "L"
      ],
      "homeFormHome": [],
      "awayFormAway": [],
      "formAdvantage": false,
      "odds": null,
      "forebet": null,
      "sofascore": null,
      "focusTeam": "home"
    },
    {
      "id": 4132897466319546771,
      "homeTeam": null,
      "awayTeam": null,
      "time": "",
      "date": "2026-02-14",
      "league": "",
      "country": "",
      "sport": "tennis",
      "matchUrl": "",
      "qualifies": false,
      "h2h": {
        "home": 0,
        "draw": 0,
        "away": 0,
        "total": 5,
        "winRate": 0
      },
      "homeForm": [],
      "awayForm": [],
      "homeFormHome": [],
      "awayFormAway": [],
      "formAdvantage": false,
      "odds": null,
      "forebet": null,
      "sofascore": null,
      "focusTeam": "home"
    },
    {
      "id": 4132897466319546771,
      "homeTeam": null,
      "awayTeam": null,
      "time": "",
      "date": "2026-02-14",
      "league": "",
      "country": "",
      "sport": "tennis",
      "matchUrl": "",
      "qualifies": false,
      "h2h": {
        "home": 0,
        "draw": 0,
        "away": 0,
        "total": 5,
        "winRate": 0
      },
      "homeForm": [],
      "awayForm": [],
      "homeFormHome": [],
      "awayFormAway": [],
      "formAdvantage": false,
      "odds": null,
      "forebet": null,
      "sofascore": null,
      "focusTeam": "home"
    },
    {
      "id": 4132897466319546771,
      "homeTeam": null,
      "awayTeam": null,
      "time": "",
      "date": "2026-02-14",
      "league": "",
      "country": "",
      "sport": "tennis",
      "matchUrl": "",
      "qualifies": false,
      "h2h": {
        "home": 0,
        "draw": 0,
        "away": 0,
        "total": 5,
        "winRate": 0
      },
      "homeForm": [],
      "awayForm": [],
      "homeFormHome": [],
      "awayFormAway": [],
      "formAdvantage": false,
      "odds": null,
      "forebet": null,
      "sofascore": null,
      "focusTeam": "home"
    },
    {
      "id": 4132897466319546771,
      "homeTeam": null,
      "awayTeam": null,
      "time": "",
      "date": "2026-02-14",
      "league": "",
      "country": "",
      "sport": "tennis",
      "matchUrl": "",
      "qualifies": false,
      "h2h": {
        "home": 0,
        "draw": 0,
        "away": 0,
        "total": 5,
        "winRate": 0
      },
      "homeForm": [],
      "awayForm": [],
      "homeFormHome": [],
      "awayFormAway": [],
      "formAdvantage": false,
      "odds": null,
      "forebet": null,
      "sofascore": null,
      "focusTeam": "home"
    },
    {
      "id": 4132897466319546771,
      "homeTeam": null,
      "awayTeam": null,
      "time": "",
      "date": "2026-02-14",
      "league": "",
      "country": "",
      "sport": "tennis",
      "matchUrl": "",
      "qualifies": false,
      "h2h": {
        "home": 0,
        "draw": 0,
        "away": 0,
        "total": 5,
        "winRate": 0
      },
      "homeForm": [],
      "awayForm": [],
      "homeFormHome": [],
      "awayFormAway": [],
      "formAdvantage": false,
      "odds": null,
      "forebet": null,
      "sofascore": null,
      "focusTeam": "home"
    },
    {
      "id": 4132897466319546771,
      "homeTeam": null,
      "awayTeam": null,
      "time": "",
      "date": "2026-02-14",
      "league": "",
      "country": "",
      "sport": "tennis",
      "matchUrl": "",
      "qualifies": false,
      "h2h": {
        "home": 0,
        "draw": 0,
        "away": 0,
        "total": 5,
        "winRate": 0
      },
      "homeForm": [],
      "awayForm": [],
      "homeFormHome": [],
      "awayFormAway": [],
      "formAdvantage": false,
      "odds": null,
      "forebet": null,
      "sofascore": null,
      "focusTeam": "home"
    },
    {
      "id": 4132897466319546771,
      "homeTeam": null,
      "awayTeam": null,
      "time": "",
      "date": "2026-02-14",
      "league": "",
      "country": "",
      "sport": "tennis",
      "matchUrl": "",
      "qualifies": false,
      "h2h": {
        "home": 0,
        "draw": 0,
        "away": 0,
        "total": 5,
        "winRate": 0
      },
      "homeForm": [],
      "awayForm": [],
      "homeFormHome": [],
      "awayFormAway": [],
      "formAdvantage": false,
      "odds": null,
      "forebet": null,
      "sofascore": null,
      "focusTeam": "home"
    },
    {
      "id": 4132897466319546771,
      "homeTeam": null,
      "awayTeam": null,
      "time": "",
      "date": "2026-02-14",
      "league": "",
      "country": "",
      "sport": "tennis",
      "matchUrl": "",
      "qualifies": false,
      "h2h": {
        "home": 0,
        "draw": 0,
        "away": 0,
        "total": 5,
        "winRate": 0
      },
      "homeForm": [],
      "awayForm": [],
      "homeFormHome": [],
      "awayFormAway": [],
      "formAdvantage": false,
      "odds": null,
      "forebet": null,
      "sofascore": null,
      "focusTeam": "home"
    },
    {
      "id": 4132897466319546771,
      "homeTeam": null,
      "awayTeam": null,
      "time": "",
      "date": "2026-02-14",
      "league": "",
      "country": "",
      "sport": "tennis",
      "matchUrl": "",
      "qualifies": false,
      "h2h": {
        "home": 0,
        "draw": 0,
        "away": 0,
        "total": 5,
        "winRate": 0
      },
      "homeForm": [],
      "awayForm": [],
      "homeFormHome": [],
      "awayFormAway": [],
      "formAdvantage": false,
      "odds": null,
      "forebet": null,
      "sofascore": null,
      "focusTeam": "home"
    },
    {
      "id": 4132897466319546771,
      "homeTeam": null,
      "awayTeam": null,
      "time": "",
      "date": "2026-02-14",
      "league": "",
      "country": "",
      "sport": "tennis",
      "matchUrl": "",
      "qualifies": false,
      "h2h": {
        "home": 0,
        "draw": 0,
        "away": 0,
        "total": 5,
        "winRate": 0
      },
      "homeForm": [],
      "awayForm": [],
      "homeFormHome": [],
      "awayFormAway": [],
      "formAdvantage": false,
      "odds": null,
      "forebet": null,
      "sofascore": null,
      "focusTeam": "home"
    },
    {
      "id": 4132897466319546771,
      "homeTeam": null,
      "awayTeam": null,
      "time": "",
      "date": "2026-02-14",
      "league": "",
      "country": "",
      "sport": "tennis",
      "matchUrl": "",
      "qualifies": false,
      "h2h": {
        "home": 0,
        "draw": 0,
        "away": 0,
        "total": 5,
        "winRate": 0
      },
      "homeForm": [],
      "awayForm": [],
      "homeFormHome": [],
      "awayFormAway": [],
      "formAdvantage": false,
      "odds": null,
      "forebet": null,
      "sofascore": null,
      "focusTeam": "home"
    },
    {
      "id": 4132897466319546771,
      "homeTeam": null,
      "awayTeam": null,
      "time": "",
      "date": "2026-02-14",
      "league": "",
      "country": "",
      "sport": "tennis",
      "matchUrl": "",
      "qualifies": false,
      "h2h": {
        "home": 0,
        "draw": 0,
        "away": 0,
        "total": 5,
        "winRate": 0
      },
      "homeForm": [],
      "awayForm": [],
      "homeFormHome": [],
      "awayFormAway": [],
      "formAdvantage": false,
      "odds": null,
      "forebet": null,
      "sofascore": null,
      "focusTeam": "home"
    },
    {
      "id": 4132897466319546771,
      "homeTeam": null,
      "awayTeam": null,
      "time": "",
      "date": "2026-02-14",
      "league": "",
      "country": "",
      "sport": "tennis",
      "matchUrl": "",
      "qualifies": false,
      "h2h": {
        "home": 0,
        "draw": 0,
        "away": 0,
        "total": 5,
        "winRate": 0
      },
      "homeForm": [],
      "awayForm": [],
      "homeFormHome": [],
      "awayFormAway": [],
      "formAdvantage": false,
      "odds": null,
      "forebet": null,
      "sofascore": null,
      "focusTeam": "home"
    },
    {
      "id": 4132897466319546771,
      "homeTeam": null,
      "awayTeam": null,
      "time": "",
      "date": "2026-02-14",
      "league": "",
      "country": "",
      "sport": "tennis",
      "matchUrl": "",
      "qualifies": false,
      "h2h": {
        "home": 0,
        "draw": 0,
        "away": 0,
        "total": 5,
        "winRate": 0
      },
      "homeForm": [],
      "awayForm": [],
      "homeFormHome": [],
      "awayFormAway": [],
      "formAdvantage": false,
      "odds": null,
      "forebet": null,
      "sofascore": null,
      "focusTeam": "home"
    },
    {
      "id": 4132897466319546771,
      "homeTeam": null,
      "awayTeam": null,
      "time": "",
      "date": "2026-02-14",
      "league": "",
      "country": "",
      "sport": "tennis",
      "matchUrl": "",
      "qualifies": false,
      "h2h": {
        "home": 0,
        "draw": 0,
        "away": 0,
        "total": 5,
        "winRate": 0
      },
      "homeForm": [],
      "awayForm": [],
      "homeFormHome": [],
      "awayFormAway": [],
      "formAdvantage": false,
      "odds": null,
      "forebet": null,
      "sofascore": null,
      "focusTeam": "home"
    },
    {
      "id": 4132897466319546771,
      "homeTeam": null,
      "awayTeam": null,
      "time": "",
      "date": "2026-02-14",
      "league": "",
      "country": "",
      "sport": "tennis",
      "matchUrl": "",
      "qualifies": false,
      "h2h": {
        "home": 0,
        "draw": 0,
        "away": 0,
        "total": 5,
        "winRate": 0
      },
      "homeForm": [],
      "awayForm": [],
      "homeFormHome": [],
      "awayFormAway": [],
      "formAdvantage": false,
      "odds": null,
      "forebet": null,
      "sofascore": null,
      "focusTeam": "home"
    },
    {
      "id": 4132897466319546771,
      "homeTeam": null,
      "awayTeam": null,
      "time": "",
      "date": "2026-02-14",
      "league": "",
      "country": "",
      "sport": "tennis",
      "matchUrl": "",
      "qualifies": false,
      "h2h": {
        "home": 0,
        "draw": 0,
        "away": 0,
        "total": 5,
        "winRate": 0
      },
      "homeForm": [],
      "awayForm": [],
      "homeFormHome": [],
      "awayFormAway": [],
      "formAdvantage": false,
      "odds": null,
      "forebet": null,
      "sofascore": null,
      "focusTeam": "home"
    },
    {
      "id": 4132897466319546771,
      "homeTeam": null,
      "awayTeam": null,
      "time": "",
      "date": "2026-02-14",
      "league": "",
      "country": "",
      "sport": "tennis",
      "matchUrl": "",
      "qualifies": false,
      "h2h": {
        "home": 0,
        "draw": 0,
        "away": 0,
        "total": 5,
        "winRate": 0
      },
      "homeForm": [],
      "awayForm": [],
      "homeFormHome": [],
      "awayFormAway": [],
      "formAdvantage": false,
      "odds": null,
      "forebet": null,
      "sofascore": null,
      "focusTeam": "home"
    },
    {
      "id": 4132897466319546771,
      "homeTeam": null,
      "awayTeam": null,
      "time": "",
      "date": "2026-02-14",
      "league": "",
      "country": "",
      "sport": "tennis",
      "matchUrl": "",
      "qualifies": false,
      "h2h": {
        "home": 0,
        "draw": 0,
        "away": 0,
        "total": 5,
        "winRate": 0
      },
      "homeForm": [],
      "awayForm": [],
      "homeFormHome": [],
      "awayFormAway": [],
      "formAdvantage": false,
      "odds": null,
      "forebet": null,
      "sofascore": null,
      "focusTeam": "home"
    },
    {
      "id": 4132897466319546771,
      "homeTeam": null,
      "awayTeam": null,
      "time": "",
      "date": "2026-02-14",
      "league": "",
      "country": "",
      "sport": "tennis",
      "matchUrl": "",
      "qualifies": false,
      "h2h": {
        "home": 0,
        "draw": 0,
        "away": 0,
        "total": 5,
        "winRate": 0
      },
      "homeForm": [],
      "awayForm": [],
      "homeFormHome": [],
      "awayFormAway": [],
      "formAdvantage": false,
      "odds": null,
      "forebet": null,
      "sofascore": null,
      "focusTeam": "home"
    },
    {
      "id": 4132897466319546771,
      "homeTeam": null,
      "awayTeam": null,
      "time": "",
      "date": "2026-02-14",
      "league": "",
      "country": "",
      "sport": "tennis",
      "matchUrl": "",
      "qualifies": false,
      "h2h": {
        "home": 0,
        "draw": 0,
        "away": 0,
        "total": 5,
        "winRate": 0
      },
      "homeForm": [],
      "awayForm": [],
      "homeFormHome": [],
      "awayFormAway": [],
      "formAdvantage": false,
      "odds": null,
      "forebet": null,
      "sofascore": null,
      "focusTeam": "home"
    }
  ]
}